edu.nyu.websocket.ChatClient.<init> : (Ljava.lang.String;)V
  0 aload_0         []::[< Ledu/nyu/websocket/ChatClient;, IP, r0 >, < Ljava/lang/String;, IP, r1 >]
  1 ldc             [< Ledu/nyu/websocket/ChatClient;, IP, r0 >]::[< Ledu/nyu/websocket/ChatClient;, IP, r0 >, < Ljava/lang/String;, IP, r1 >]
  3 invokespecial   [< Ledu/nyu/websocket/ChatClient;, IP, r0 >, < Ljava/lang/String;, "WebSocket Chat Client" >]::[< Ledu/nyu/websocket/ChatClient;, IP, r0 >, < Ljava/lang/String;, IP, r1 >]
  6 aload_0         []::[< Ledu/nyu/websocket/ChatClient;, IP, r0 >, < Ljava/lang/String;, IP, r1 >]
  7 invokevirtual   [< Ledu/nyu/websocket/ChatClient;, IP, r0 >]::[< Ledu/nyu/websocket/ChatClient;, IP, r0 >, < Ljava/lang/String;, IP, r1 >]
 10 astore_2        [< Ljava/awt/Container;, return value from javax.swing.JFrame.getContentPane()Ljava/awt/Container; >]::[< Ledu/nyu/websocket/ChatClient;, IP, r0 >, < Ljava/lang/String;, IP, r1 >]
 11 new             []::[< Ledu/nyu/websocket/ChatClient;, IP, r0 >, < Ljava/lang/String;, IP, r1 >, < Ljava/awt/Container;, return value from javax.swing.JFrame.getContentPane()Ljava/awt/Container;, r2 >]
 14 dup             [< Ljava/awt/GridLayout;, new >]::[< Ledu/nyu/websocket/ChatClient;, IP, r0 >, < Ljava/lang/String;, IP, r1 >, < Ljava/awt/Container;, return value from javax.swing.JFrame.getContentPane()Ljava/awt/Container;, r2 >]
 15 invokespecial   [< Ljava/awt/GridLayout;, new >, < Ljava/awt/GridLayout;, new >]::[< Ledu/nyu/websocket/ChatClient;, IP, r0 >, < Ljava/lang/String;, IP, r1 >, < Ljava/awt/Container;, return value from javax.swing.JFrame.getContentPane()Ljava/awt/Container;, r2 >]
 18 astore_3        [< Ljava/awt/GridLayout;, new, return value from java.awt.GridLayout.<init>()V >]::[< Ledu/nyu/websocket/ChatClient;, IP, r0 >, < Ljava/lang/String;, IP, r1 >, < Ljava/awt/Container;, return value from javax.swing.JFrame.getContentPane()Ljava/awt/Container;, r2 >]
 19 aload_3         []::[< Ledu/nyu/websocket/ChatClient;, IP, r0 >, < Ljava/lang/String;, IP, r1 >, < Ljava/awt/Container;, return value from javax.swing.JFrame.getContentPane()Ljava/awt/Container;, r2 >, < Ljava/awt/GridLayout;, new, return value from java.awt.GridLayout.<init>()V, r3 >]
 20 iconst_1        [< Ljava/awt/GridLayout;, new, return value from java.awt.GridLayout.<init>()V, r3 >]::[< Ledu/nyu/websocket/ChatClient;, IP, r0 >, < Ljava/lang/String;, IP, r1 >, < Ljava/awt/Container;, return value from javax.swing.JFrame.getContentPane()Ljava/awt/Container;, r2 >, < Ljava/awt/GridLayout;, new, return value from java.awt.GridLayout.<init>()V, r3 >]
 21 invokevirtual   [< Ljava/awt/GridLayout;, new, return value from java.awt.GridLayout.<init>()V, r3 >, < I, 1 >]::[< Ledu/nyu/websocket/ChatClient;, IP, r0 >, < Ljava/lang/String;, IP, r1 >, < Ljava/awt/Container;, return value from javax.swing.JFrame.getContentPane()Ljava/awt/Container;, r2 >, < Ljava/awt/GridLayout;, new, return value from java.awt.GridLayout.<init>()V, r3 >]
 24 aload_3         []::[< Ledu/nyu/websocket/ChatClient;, IP, r0 >, < Ljava/lang/String;, IP, r1 >, < Ljava/awt/Container;, return value from javax.swing.JFrame.getContentPane()Ljava/awt/Container;, r2 >, < Ljava/awt/GridLayout;, new, return value from java.awt.GridLayout.<init>()V, r3 >]
 25 bipush          [< Ljava/awt/GridLayout;, new, return value from java.awt.GridLayout.<init>()V, r3 >]::[< Ledu/nyu/websocket/ChatClient;, IP, r0 >, < Ljava/lang/String;, IP, r1 >, < Ljava/awt/Container;, return value from javax.swing.JFrame.getContentPane()Ljava/awt/Container;, r2 >, < Ljava/awt/GridLayout;, new, return value from java.awt.GridLayout.<init>()V, r3 >]
 27 invokevirtual   [< Ljava/awt/GridLayout;, new, return value from java.awt.GridLayout.<init>()V, r3 >, < I, 6 >]::[< Ledu/nyu/websocket/ChatClient;, IP, r0 >, < Ljava/lang/String;, IP, r1 >, < Ljava/awt/Container;, return value from javax.swing.JFrame.getContentPane()Ljava/awt/Container;, r2 >, < Ljava/awt/GridLayout;, new, return value from java.awt.GridLayout.<init>()V, r3 >]
 30 aload_2         []::[< Ledu/nyu/websocket/ChatClient;, IP, r0 >, < Ljava/lang/String;, IP, r1 >, < Ljava/awt/Container;, return value from javax.swing.JFrame.getContentPane()Ljava/awt/Container;, r2 >, < Ljava/awt/GridLayout;, new, return value from java.awt.GridLayout.<init>()V, r3 >]
 31 aload_3         [< Ljava/awt/Container;, return value from javax.swing.JFrame.getContentPane()Ljava/awt/Container;, r2 >]::[< Ledu/nyu/websocket/ChatClient;, IP, r0 >, < Ljava/lang/String;, IP, r1 >, < Ljava/awt/Container;, return value from javax.swing.JFrame.getContentPane()Ljava/awt/Container;, r2 >, < Ljava/awt/GridLayout;, new, return value from java.awt.GridLayout.<init>()V, r3 >]
 32 invokevirtual   [< Ljava/awt/Container;, return value from javax.swing.JFrame.getContentPane()Ljava/awt/Container;, r2 >, < Ljava/awt/GridLayout;, new, return value from java.awt.GridLayout.<init>()V, r3 >]::[< Ledu/nyu/websocket/ChatClient;, IP, r0 >, < Ljava/lang/String;, IP, r1 >, < Ljava/awt/Container;, return value from javax.swing.JFrame.getContentPane()Ljava/awt/Container;, r2 >, < Ljava/awt/GridLayout;, new, return value from java.awt.GridLayout.<init>()V, r3 >]
 35 iconst_1        []::[< Ledu/nyu/websocket/ChatClient;, IP, r0 >, < Ljava/lang/String;, IP, r1 >, < Ljava/awt/Container;, return value from javax.swing.JFrame.getContentPane()Ljava/awt/Container;, r2 >, < Ljava/awt/GridLayout;, new, return value from java.awt.GridLayout.<init>()V, r3 >]
 36 anewarray       [< I, 1 >]::[< Ledu/nyu/websocket/ChatClient;, IP, r0 >, < Ljava/lang/String;, IP, r1 >, < Ljava/awt/Container;, return value from javax.swing.JFrame.getContentPane()Ljava/awt/Container;, r2 >, < Ljava/awt/GridLayout;, new, return value from java.awt.GridLayout.<init>()V, r3 >]
 39 dup             [< [Lorg/java_websocket/drafts/Draft;, new, 1 >]::[< Ledu/nyu/websocket/ChatClient;, IP, r0 >, < Ljava/lang/String;, IP, r1 >, < Ljava/awt/Container;, return value from javax.swing.JFrame.getContentPane()Ljava/awt/Container;, r2 >, < Ljava/awt/GridLayout;, new, return value from java.awt.GridLayout.<init>()V, r3 >]
 40 iconst_0        [< [Lorg/java_websocket/drafts/Draft;, new, 1 >, < [Lorg/java_websocket/drafts/Draft;, new, 1 >]::[< Ledu/nyu/websocket/ChatClient;, IP, r0 >, < Ljava/lang/String;, IP, r1 >, < Ljava/awt/Container;, return value from javax.swing.JFrame.getContentPane()Ljava/awt/Container;, r2 >, < Ljava/awt/GridLayout;, new, return value from java.awt.GridLayout.<init>()V, r3 >]
 41 new             [< [Lorg/java_websocket/drafts/Draft;, new, 1 >, < [Lorg/java_websocket/drafts/Draft;, new, 1 >, < I, 0 >]::[< Ledu/nyu/websocket/ChatClient;, IP, r0 >, < Ljava/lang/String;, IP, r1 >, < Ljava/awt/Container;, return value from javax.swing.JFrame.getContentPane()Ljava/awt/Container;, r2 >, < Ljava/awt/GridLayout;, new, return value from java.awt.GridLayout.<init>()V, r3 >]
 44 dup             [< [Lorg/java_websocket/drafts/Draft;, new, 1 >, < [Lorg/java_websocket/drafts/Draft;, new, 1 >, < I, 0 >, < Lorg/java_websocket/drafts/Draft_6455;, new >]::[< Ledu/nyu/websocket/ChatClient;, IP, r0 >, < Ljava/lang/String;, IP, r1 >, < Ljava/awt/Container;, return value from javax.swing.JFrame.getContentPane()Ljava/awt/Container;, r2 >, < Ljava/awt/GridLayout;, new, return value from java.awt.GridLayout.<init>()V, r3 >]
 45 invokespecial   [< [Lorg/java_websocket/drafts/Draft;, new, 1 >, < [Lorg/java_websocket/drafts/Draft;, new, 1 >, < I, 0 >, < Lorg/java_websocket/drafts/Draft_6455;, new >, < Lorg/java_websocket/drafts/Draft_6455;, new >]::[< Ledu/nyu/websocket/ChatClient;, IP, r0 >, < Ljava/lang/String;, IP, r1 >, < Ljava/awt/Container;, return value from javax.swing.JFrame.getContentPane()Ljava/awt/Container;, r2 >, < Ljava/awt/GridLayout;, new, return value from java.awt.GridLayout.<init>()V, r3 >]
 48 aastore         [< [Lorg/java_websocket/drafts/Draft;, new, 1 >, < [Lorg/java_websocket/drafts/Draft;, new, 1 >, < I, 0 >, < Lorg/java_websocket/drafts/Draft_6455;, new, return value from org.java_websocket.drafts.Draft_6455.<init>() >]::[< Ledu/nyu/websocket/ChatClient;, IP, r0 >, < Ljava/lang/String;, IP, r1 >, < Ljava/awt/Container;, return value from javax.swing.JFrame.getContentPane()Ljava/awt/Container;, r2 >, < Ljava/awt/GridLayout;, new, return value from java.awt.GridLayout.<init>()V, r3 >]
 49 astore          [< [Lorg/java_websocket/drafts/Draft;, new, 1 >]::[< Ledu/nyu/websocket/ChatClient;, IP, r0 >, < Ljava/lang/String;, IP, r1 >, < Ljava/awt/Container;, return value from javax.swing.JFrame.getContentPane()Ljava/awt/Container;, r2 >, < Ljava/awt/GridLayout;, new, return value from java.awt.GridLayout.<init>()V, r3 >]
 51 aload_0         []::[< Ledu/nyu/websocket/ChatClient;, IP, r0 >, < Ljava/lang/String;, IP, r1 >, < Ljava/awt/Container;, return value from javax.swing.JFrame.getContentPane()Ljava/awt/Container;, r2 >, < Ljava/awt/GridLayout;, new, return value from java.awt.GridLayout.<init>()V, r3 >, < [Lorg/java_websocket/drafts/Draft;, new, 1, r4 >]
 52 new             [< Ledu/nyu/websocket/ChatClient;, IP, r0 >]::[< Ledu/nyu/websocket/ChatClient;, IP, r0 >, < Ljava/lang/String;, IP, r1 >, < Ljava/awt/Container;, return value from javax.swing.JFrame.getContentPane()Ljava/awt/Container;, r2 >, < Ljava/awt/GridLayout;, new, return value from java.awt.GridLayout.<init>()V, r3 >, < [Lorg/java_websocket/drafts/Draft;, new, 1, r4 >]
 55 dup             [< Ledu/nyu/websocket/ChatClient;, IP, r0 >, < Ljavax/swing/JComboBox;, new >]::[< Ledu/nyu/websocket/ChatClient;, IP, r0 >, < Ljava/lang/String;, IP, r1 >, < Ljava/awt/Container;, return value from javax.swing.JFrame.getContentPane()Ljava/awt/Container;, r2 >, < Ljava/awt/GridLayout;, new, return value from java.awt.GridLayout.<init>()V, r3 >, < [Lorg/java_websocket/drafts/Draft;, new, 1, r4 >]
 56 aload           [< Ledu/nyu/websocket/ChatClient;, IP, r0 >, < Ljavax/swing/JComboBox;, new >, < Ljavax/swing/JComboBox;, new >]::[< Ledu/nyu/websocket/ChatClient;, IP, r0 >, < Ljava/lang/String;, IP, r1 >, < Ljava/awt/Container;, return value from javax.swing.JFrame.getContentPane()Ljava/awt/Container;, r2 >, < Ljava/awt/GridLayout;, new, return value from java.awt.GridLayout.<init>()V, r3 >, < [Lorg/java_websocket/drafts/Draft;, new, 1, r4 >]
 58 invokespecial   [< Ledu/nyu/websocket/ChatClient;, IP, r0 >, < Ljavax/swing/JComboBox;, new >, < Ljavax/swing/JComboBox;, new >, < [Lorg/java_websocket/drafts/Draft;, new, 1, r4 >]::[< Ledu/nyu/websocket/ChatClient;, IP, r0 >, < Ljava/lang/String;, IP, r1 >, < Ljava/awt/Container;, return value from javax.swing.JFrame.getContentPane()Ljava/awt/Container;, r2 >, < Ljava/awt/GridLayout;, new, return value from java.awt.GridLayout.<init>()V, r3 >, < [Lorg/java_websocket/drafts/Draft;, new, 1, r4 >]
 61 putfield        [< Ledu/nyu/websocket/ChatClient;, IP, r0 >, < Ljavax/swing/JComboBox;, new, return value from javax.swing.JComboBox.<init>([Ljava/lang/Object;)V >]::[< Ledu/nyu/websocket/ChatClient;, IP, r0 >, < Ljava/lang/String;, IP, r1 >, < Ljava/awt/Container;, return value from javax.swing.JFrame.getContentPane()Ljava/awt/Container;, r2 >, < Ljava/awt/GridLayout;, new, return value from java.awt.GridLayout.<init>()V, r3 >, < [Lorg/java_websocket/drafts/Draft;, new, 1, r4 >]
 64 aload_2         []::[< Ledu/nyu/websocket/ChatClient;, IP, r0 >, < Ljava/lang/String;, IP, r1 >, < Ljava/awt/Container;, return value from javax.swing.JFrame.getContentPane()Ljava/awt/Container;, r2 >, < Ljava/awt/GridLayout;, new, return value from java.awt.GridLayout.<init>()V, r3 >, < [Lorg/java_websocket/drafts/Draft;, new, 1, r4 >]
 65 aload_0         [< Ljava/awt/Container;, return value from javax.swing.JFrame.getContentPane()Ljava/awt/Container;, r2 >]::[< Ledu/nyu/websocket/ChatClient;, IP, r0 >, < Ljava/lang/String;, IP, r1 >, < Ljava/awt/Container;, return value from javax.swing.JFrame.getContentPane()Ljava/awt/Container;, r2 >, < Ljava/awt/GridLayout;, new, return value from java.awt.GridLayout.<init>()V, r3 >, < [Lorg/java_websocket/drafts/Draft;, new, 1, r4 >]
 66 getfield        [< Ljava/awt/Container;, return value from javax.swing.JFrame.getContentPane()Ljava/awt/Container;, r2 >, < Ledu/nyu/websocket/ChatClient;, IP, r0 >]::[< Ledu/nyu/websocket/ChatClient;, IP, r0 >, < Ljava/lang/String;, IP, r1 >, < Ljava/awt/Container;, return value from javax.swing.JFrame.getContentPane()Ljava/awt/Container;, r2 >, < Ljava/awt/GridLayout;, new, return value from java.awt.GridLayout.<init>()V, r3 >, < [Lorg/java_websocket/drafts/Draft;, new, 1, r4 >]
 69 invokevirtual   [< Ljava/awt/Container;, return value from javax.swing.JFrame.getContentPane()Ljava/awt/Container;, r2 >, < Ljavax/swing/JComboBox;, 0:edu.nyu.websocket.ChatClient.draft Ljavax/swing/JComboBox; >]::[< Ledu/nyu/websocket/ChatClient;, IP, r0 >, < Ljava/lang/String;, IP, r1 >, < Ljava/awt/Container;, return value from javax.swing.JFrame.getContentPane()Ljava/awt/Container;, r2 >, < Ljava/awt/GridLayout;, new, return value from java.awt.GridLayout.<init>()V, r3 >, < [Lorg/java_websocket/drafts/Draft;, new, 1, r4 >]
 72 pop             [< Ljava/awt/Component;, return value from java.awt.Container.add(Ljava/awt/Component;)Ljava/awt/Component; >]::[< Ledu/nyu/websocket/ChatClient;, IP, r0 >, < Ljava/lang/String;, IP, r1 >, < Ljava/awt/Container;, return value from javax.swing.JFrame.getContentPane()Ljava/awt/Container;, r2 >, < Ljava/awt/GridLayout;, new, return value from java.awt.GridLayout.<init>()V, r3 >, < [Lorg/java_websocket/drafts/Draft;, new, 1, r4 >]
 73 aload_0         []::[< Ledu/nyu/websocket/ChatClient;, IP, r0 >, < Ljava/lang/String;, IP, r1 >, < Ljava/awt/Container;, return value from javax.swing.JFrame.getContentPane()Ljava/awt/Container;, r2 >, < Ljava/awt/GridLayout;, new, return value from java.awt.GridLayout.<init>()V, r3 >, < [Lorg/java_websocket/drafts/Draft;, new, 1, r4 >]
 74 new             [< Ledu/nyu/websocket/ChatClient;, IP, r0 >]::[< Ledu/nyu/websocket/ChatClient;, IP, r0 >, < Ljava/lang/String;, IP, r1 >, < Ljava/awt/Container;, return value from javax.swing.JFrame.getContentPane()Ljava/awt/Container;, r2 >, < Ljava/awt/GridLayout;, new, return value from java.awt.GridLayout.<init>()V, r3 >, < [Lorg/java_websocket/drafts/Draft;, new, 1, r4 >]
 77 dup             [< Ledu/nyu/websocket/ChatClient;, IP, r0 >, < Ljavax/swing/JTextField;, new >]::[< Ledu/nyu/websocket/ChatClient;, IP, r0 >, < Ljava/lang/String;, IP, r1 >, < Ljava/awt/Container;, return value from javax.swing.JFrame.getContentPane()Ljava/awt/Container;, r2 >, < Ljava/awt/GridLayout;, new, return value from java.awt.GridLayout.<init>()V, r3 >, < [Lorg/java_websocket/drafts/Draft;, new, 1, r4 >]
 78 invokespecial   [< Ledu/nyu/websocket/ChatClient;, IP, r0 >, < Ljavax/swing/JTextField;, new >, < Ljavax/swing/JTextField;, new >]::[< Ledu/nyu/websocket/ChatClient;, IP, r0 >, < Ljava/lang/String;, IP, r1 >, < Ljava/awt/Container;, return value from javax.swing.JFrame.getContentPane()Ljava/awt/Container;, r2 >, < Ljava/awt/GridLayout;, new, return value from java.awt.GridLayout.<init>()V, r3 >, < [Lorg/java_websocket/drafts/Draft;, new, 1, r4 >]
 81 putfield        [< Ledu/nyu/websocket/ChatClient;, IP, r0 >, < Ljavax/swing/JTextField;, new, return value from javax.swing.JTextField.<init>()V >]::[< Ledu/nyu/websocket/ChatClient;, IP, r0 >, < Ljava/lang/String;, IP, r1 >, < Ljava/awt/Container;, return value from javax.swing.JFrame.getContentPane()Ljava/awt/Container;, r2 >, < Ljava/awt/GridLayout;, new, return value from java.awt.GridLayout.<init>()V, r3 >, < [Lorg/java_websocket/drafts/Draft;, new, 1, r4 >]
 84 aload_0         []::[< Ledu/nyu/websocket/ChatClient;, IP, r0 >, < Ljava/lang/String;, IP, r1 >, < Ljava/awt/Container;, return value from javax.swing.JFrame.getContentPane()Ljava/awt/Container;, r2 >, < Ljava/awt/GridLayout;, new, return value from java.awt.GridLayout.<init>()V, r3 >, < [Lorg/java_websocket/drafts/Draft;, new, 1, r4 >]
 85 getfield        [< Ledu/nyu/websocket/ChatClient;, IP, r0 >]::[< Ledu/nyu/websocket/ChatClient;, IP, r0 >, < Ljava/lang/String;, IP, r1 >, < Ljava/awt/Container;, return value from javax.swing.JFrame.getContentPane()Ljava/awt/Container;, r2 >, < Ljava/awt/GridLayout;, new, return value from java.awt.GridLayout.<init>()V, r3 >, < [Lorg/java_websocket/drafts/Draft;, new, 1, r4 >]
 88 aload_1         [< Ljavax/swing/JTextField;, 0:edu.nyu.websocket.ChatClient.uriField Ljavax/swing/JTextField; >]::[< Ledu/nyu/websocket/ChatClient;, IP, r0 >, < Ljava/lang/String;, IP, r1 >, < Ljava/awt/Container;, return value from javax.swing.JFrame.getContentPane()Ljava/awt/Container;, r2 >, < Ljava/awt/GridLayout;, new, return value from java.awt.GridLayout.<init>()V, r3 >, < [Lorg/java_websocket/drafts/Draft;, new, 1, r4 >]
 89 invokevirtual   [< Ljavax/swing/JTextField;, 0:edu.nyu.websocket.ChatClient.uriField Ljavax/swing/JTextField; >, < Ljava/lang/String;, IP, r1 >]::[< Ledu/nyu/websocket/ChatClient;, IP, r0 >, < Ljava/lang/String;, IP, r1 >, < Ljava/awt/Container;, return value from javax.swing.JFrame.getContentPane()Ljava/awt/Container;, r2 >, < Ljava/awt/GridLayout;, new, return value from java.awt.GridLayout.<init>()V, r3 >, < [Lorg/java_websocket/drafts/Draft;, new, 1, r4 >]
 92 aload_2         []::[< Ledu/nyu/websocket/ChatClient;, IP, r0 >, < Ljava/lang/String;, IP, r1 >, < Ljava/awt/Container;, return value from javax.swing.JFrame.getContentPane()Ljava/awt/Container;, r2 >, < Ljava/awt/GridLayout;, new, return value from java.awt.GridLayout.<init>()V, r3 >, < [Lorg/java_websocket/drafts/Draft;, new, 1, r4 >]
 93 aload_0         [< Ljava/awt/Container;, return value from javax.swing.JFrame.getContentPane()Ljava/awt/Container;, r2 >]::[< Ledu/nyu/websocket/ChatClient;, IP, r0 >, < Ljava/lang/String;, IP, r1 >, < Ljava/awt/Container;, return value from javax.swing.JFrame.getContentPane()Ljava/awt/Container;, r2 >, < Ljava/awt/GridLayout;, new, return value from java.awt.GridLayout.<init>()V, r3 >, < [Lorg/java_websocket/drafts/Draft;, new, 1, r4 >]
 94 getfield        [< Ljava/awt/Container;, return value from javax.swing.JFrame.getContentPane()Ljava/awt/Container;, r2 >, < Ledu/nyu/websocket/ChatClient;, IP, r0 >]::[< Ledu/nyu/websocket/ChatClient;, IP, r0 >, < Ljava/lang/String;, IP, r1 >, < Ljava/awt/Container;, return value from javax.swing.JFrame.getContentPane()Ljava/awt/Container;, r2 >, < Ljava/awt/GridLayout;, new, return value from java.awt.GridLayout.<init>()V, r3 >, < [Lorg/java_websocket/drafts/Draft;, new, 1, r4 >]
 97 invokevirtual   [< Ljava/awt/Container;, return value from javax.swing.JFrame.getContentPane()Ljava/awt/Container;, r2 >, < Ljavax/swing/JTextField;, 0:edu.nyu.websocket.ChatClient.uriField Ljavax/swing/JTextField; >]::[< Ledu/nyu/websocket/ChatClient;, IP, r0 >, < Ljava/lang/String;, IP, r1 >, < Ljava/awt/Container;, return value from javax.swing.JFrame.getContentPane()Ljava/awt/Container;, r2 >, < Ljava/awt/GridLayout;, new, return value from java.awt.GridLayout.<init>()V, r3 >, < [Lorg/java_websocket/drafts/Draft;, new, 1, r4 >]
100 pop             [< Ljava/awt/Component;, return value from java.awt.Container.add(Ljava/awt/Component;)Ljava/awt/Component; >]::[< Ledu/nyu/websocket/ChatClient;, IP, r0 >, < Ljava/lang/String;, IP, r1 >, < Ljava/awt/Container;, return value from javax.swing.JFrame.getContentPane()Ljava/awt/Container;, r2 >, < Ljava/awt/GridLayout;, new, return value from java.awt.GridLayout.<init>()V, r3 >, < [Lorg/java_websocket/drafts/Draft;, new, 1, r4 >]
101 aload_0         []::[< Ledu/nyu/websocket/ChatClient;, IP, r0 >, < Ljava/lang/String;, IP, r1 >, < Ljava/awt/Container;, return value from javax.swing.JFrame.getContentPane()Ljava/awt/Container;, r2 >, < Ljava/awt/GridLayout;, new, return value from java.awt.GridLayout.<init>()V, r3 >, < [Lorg/java_websocket/drafts/Draft;, new, 1, r4 >]
102 new             [< Ledu/nyu/websocket/ChatClient;, IP, r0 >]::[< Ledu/nyu/websocket/ChatClient;, IP, r0 >, < Ljava/lang/String;, IP, r1 >, < Ljava/awt/Container;, return value from javax.swing.JFrame.getContentPane()Ljava/awt/Container;, r2 >, < Ljava/awt/GridLayout;, new, return value from java.awt.GridLayout.<init>()V, r3 >, < [Lorg/java_websocket/drafts/Draft;, new, 1, r4 >]
105 dup             [< Ledu/nyu/websocket/ChatClient;, IP, r0 >, < Ljavax/swing/JButton;, new >]::[< Ledu/nyu/websocket/ChatClient;, IP, r0 >, < Ljava/lang/String;, IP, r1 >, < Ljava/awt/Container;, return value from javax.swing.JFrame.getContentPane()Ljava/awt/Container;, r2 >, < Ljava/awt/GridLayout;, new, return value from java.awt.GridLayout.<init>()V, r3 >, < [Lorg/java_websocket/drafts/Draft;, new, 1, r4 >]
106 ldc             [< Ledu/nyu/websocket/ChatClient;, IP, r0 >, < Ljavax/swing/JButton;, new >, < Ljavax/swing/JButton;, new >]::[< Ledu/nyu/websocket/ChatClient;, IP, r0 >, < Ljava/lang/String;, IP, r1 >, < Ljava/awt/Container;, return value from javax.swing.JFrame.getContentPane()Ljava/awt/Container;, r2 >, < Ljava/awt/GridLayout;, new, return value from java.awt.GridLayout.<init>()V, r3 >, < [Lorg/java_websocket/drafts/Draft;, new, 1, r4 >]
108 invokespecial   [< Ledu/nyu/websocket/ChatClient;, IP, r0 >, < Ljavax/swing/JButton;, new >, < Ljavax/swing/JButton;, new >, < Ljava/lang/String;, "Connect" >]::[< Ledu/nyu/websocket/ChatClient;, IP, r0 >, < Ljava/lang/String;, IP, r1 >, < Ljava/awt/Container;, return value from javax.swing.JFrame.getContentPane()Ljava/awt/Container;, r2 >, < Ljava/awt/GridLayout;, new, return value from java.awt.GridLayout.<init>()V, r3 >, < [Lorg/java_websocket/drafts/Draft;, new, 1, r4 >]
111 putfield        [< Ledu/nyu/websocket/ChatClient;, IP, r0 >, < Ljavax/swing/JButton;, new, return value from javax.swing.JButton.<init>(Ljava/lang/String;)V >]::[< Ledu/nyu/websocket/ChatClient;, IP, r0 >, < Ljava/lang/String;, IP, r1 >, < Ljava/awt/Container;, return value from javax.swing.JFrame.getContentPane()Ljava/awt/Container;, r2 >, < Ljava/awt/GridLayout;, new, return value from java.awt.GridLayout.<init>()V, r3 >, < [Lorg/java_websocket/drafts/Draft;, new, 1, r4 >]
114 aload_0         []::[< Ledu/nyu/websocket/ChatClient;, IP, r0 >, < Ljava/lang/String;, IP, r1 >, < Ljava/awt/Container;, return value from javax.swing.JFrame.getContentPane()Ljava/awt/Container;, r2 >, < Ljava/awt/GridLayout;, new, return value from java.awt.GridLayout.<init>()V, r3 >, < [Lorg/java_websocket/drafts/Draft;, new, 1, r4 >]
115 getfield        [< Ledu/nyu/websocket/ChatClient;, IP, r0 >]::[< Ledu/nyu/websocket/ChatClient;, IP, r0 >, < Ljava/lang/String;, IP, r1 >, < Ljava/awt/Container;, return value from javax.swing.JFrame.getContentPane()Ljava/awt/Container;, r2 >, < Ljava/awt/GridLayout;, new, return value from java.awt.GridLayout.<init>()V, r3 >, < [Lorg/java_websocket/drafts/Draft;, new, 1, r4 >]
118 aload_0         [< Ljavax/swing/JButton;, 0:edu.nyu.websocket.ChatClient.connect Ljavax/swing/JButton; >]::[< Ledu/nyu/websocket/ChatClient;, IP, r0 >, < Ljava/lang/String;, IP, r1 >, < Ljava/awt/Container;, return value from javax.swing.JFrame.getContentPane()Ljava/awt/Container;, r2 >, < Ljava/awt/GridLayout;, new, return value from java.awt.GridLayout.<init>()V, r3 >, < [Lorg/java_websocket/drafts/Draft;, new, 1, r4 >]
119 invokevirtual   [< Ljavax/swing/JButton;, 0:edu.nyu.websocket.ChatClient.connect Ljavax/swing/JButton; >, < Ledu/nyu/websocket/ChatClient;, IP, r0 >]::[< Ledu/nyu/websocket/ChatClient;, IP, r0 >, < Ljava/lang/String;, IP, r1 >, < Ljava/awt/Container;, return value from javax.swing.JFrame.getContentPane()Ljava/awt/Container;, r2 >, < Ljava/awt/GridLayout;, new, return value from java.awt.GridLayout.<init>()V, r3 >, < [Lorg/java_websocket/drafts/Draft;, new, 1, r4 >]
122 aload_2         []::[< Ledu/nyu/websocket/ChatClient;, IP, r0 >, < Ljava/lang/String;, IP, r1 >, < Ljava/awt/Container;, return value from javax.swing.JFrame.getContentPane()Ljava/awt/Container;, r2 >, < Ljava/awt/GridLayout;, new, return value from java.awt.GridLayout.<init>()V, r3 >, < [Lorg/java_websocket/drafts/Draft;, new, 1, r4 >]
123 aload_0         [< Ljava/awt/Container;, return value from javax.swing.JFrame.getContentPane()Ljava/awt/Container;, r2 >]::[< Ledu/nyu/websocket/ChatClient;, IP, r0 >, < Ljava/lang/String;, IP, r1 >, < Ljava/awt/Container;, return value from javax.swing.JFrame.getContentPane()Ljava/awt/Container;, r2 >, < Ljava/awt/GridLayout;, new, return value from java.awt.GridLayout.<init>()V, r3 >, < [Lorg/java_websocket/drafts/Draft;, new, 1, r4 >]
124 getfield        [< Ljava/awt/Container;, return value from javax.swing.JFrame.getContentPane()Ljava/awt/Container;, r2 >, < Ledu/nyu/websocket/ChatClient;, IP, r0 >]::[< Ledu/nyu/websocket/ChatClient;, IP, r0 >, < Ljava/lang/String;, IP, r1 >, < Ljava/awt/Container;, return value from javax.swing.JFrame.getContentPane()Ljava/awt/Container;, r2 >, < Ljava/awt/GridLayout;, new, return value from java.awt.GridLayout.<init>()V, r3 >, < [Lorg/java_websocket/drafts/Draft;, new, 1, r4 >]
127 invokevirtual   [< Ljava/awt/Container;, return value from javax.swing.JFrame.getContentPane()Ljava/awt/Container;, r2 >, < Ljavax/swing/JButton;, 0:edu.nyu.websocket.ChatClient.connect Ljavax/swing/JButton; >]::[< Ledu/nyu/websocket/ChatClient;, IP, r0 >, < Ljava/lang/String;, IP, r1 >, < Ljava/awt/Container;, return value from javax.swing.JFrame.getContentPane()Ljava/awt/Container;, r2 >, < Ljava/awt/GridLayout;, new, return value from java.awt.GridLayout.<init>()V, r3 >, < [Lorg/java_websocket/drafts/Draft;, new, 1, r4 >]
130 pop             [< Ljava/awt/Component;, return value from java.awt.Container.add(Ljava/awt/Component;)Ljava/awt/Component; >]::[< Ledu/nyu/websocket/ChatClient;, IP, r0 >, < Ljava/lang/String;, IP, r1 >, < Ljava/awt/Container;, return value from javax.swing.JFrame.getContentPane()Ljava/awt/Container;, r2 >, < Ljava/awt/GridLayout;, new, return value from java.awt.GridLayout.<init>()V, r3 >, < [Lorg/java_websocket/drafts/Draft;, new, 1, r4 >]
131 aload_0         []::[< Ledu/nyu/websocket/ChatClient;, IP, r0 >, < Ljava/lang/String;, IP, r1 >, < Ljava/awt/Container;, return value from javax.swing.JFrame.getContentPane()Ljava/awt/Container;, r2 >, < Ljava/awt/GridLayout;, new, return value from java.awt.GridLayout.<init>()V, r3 >, < [Lorg/java_websocket/drafts/Draft;, new, 1, r4 >]
132 new             [< Ledu/nyu/websocket/ChatClient;, IP, r0 >]::[< Ledu/nyu/websocket/ChatClient;, IP, r0 >, < Ljava/lang/String;, IP, r1 >, < Ljava/awt/Container;, return value from javax.swing.JFrame.getContentPane()Ljava/awt/Container;, r2 >, < Ljava/awt/GridLayout;, new, return value from java.awt.GridLayout.<init>()V, r3 >, < [Lorg/java_websocket/drafts/Draft;, new, 1, r4 >]
135 dup             [< Ledu/nyu/websocket/ChatClient;, IP, r0 >, < Ljavax/swing/JButton;, new >]::[< Ledu/nyu/websocket/ChatClient;, IP, r0 >, < Ljava/lang/String;, IP, r1 >, < Ljava/awt/Container;, return value from javax.swing.JFrame.getContentPane()Ljava/awt/Container;, r2 >, < Ljava/awt/GridLayout;, new, return value from java.awt.GridLayout.<init>()V, r3 >, < [Lorg/java_websocket/drafts/Draft;, new, 1, r4 >]
136 ldc             [< Ledu/nyu/websocket/ChatClient;, IP, r0 >, < Ljavax/swing/JButton;, new >, < Ljavax/swing/JButton;, new >]::[< Ledu/nyu/websocket/ChatClient;, IP, r0 >, < Ljava/lang/String;, IP, r1 >, < Ljava/awt/Container;, return value from javax.swing.JFrame.getContentPane()Ljava/awt/Container;, r2 >, < Ljava/awt/GridLayout;, new, return value from java.awt.GridLayout.<init>()V, r3 >, < [Lorg/java_websocket/drafts/Draft;, new, 1, r4 >]
138 invokespecial   [< Ledu/nyu/websocket/ChatClient;, IP, r0 >, < Ljavax/swing/JButton;, new >, < Ljavax/swing/JButton;, new >, < Ljava/lang/String;, "Close" >]::[< Ledu/nyu/websocket/ChatClient;, IP, r0 >, < Ljava/lang/String;, IP, r1 >, < Ljava/awt/Container;, return value from javax.swing.JFrame.getContentPane()Ljava/awt/Container;, r2 >, < Ljava/awt/GridLayout;, new, return value from java.awt.GridLayout.<init>()V, r3 >, < [Lorg/java_websocket/drafts/Draft;, new, 1, r4 >]
141 putfield        [< Ledu/nyu/websocket/ChatClient;, IP, r0 >, < Ljavax/swing/JButton;, new, return value from javax.swing.JButton.<init>(Ljava/lang/String;)V >]::[< Ledu/nyu/websocket/ChatClient;, IP, r0 >, < Ljava/lang/String;, IP, r1 >, < Ljava/awt/Container;, return value from javax.swing.JFrame.getContentPane()Ljava/awt/Container;, r2 >, < Ljava/awt/GridLayout;, new, return value from java.awt.GridLayout.<init>()V, r3 >, < [Lorg/java_websocket/drafts/Draft;, new, 1, r4 >]
144 aload_0         []::[< Ledu/nyu/websocket/ChatClient;, IP, r0 >, < Ljava/lang/String;, IP, r1 >, < Ljava/awt/Container;, return value from javax.swing.JFrame.getContentPane()Ljava/awt/Container;, r2 >, < Ljava/awt/GridLayout;, new, return value from java.awt.GridLayout.<init>()V, r3 >, < [Lorg/java_websocket/drafts/Draft;, new, 1, r4 >]
145 getfield        [< Ledu/nyu/websocket/ChatClient;, IP, r0 >]::[< Ledu/nyu/websocket/ChatClient;, IP, r0 >, < Ljava/lang/String;, IP, r1 >, < Ljava/awt/Container;, return value from javax.swing.JFrame.getContentPane()Ljava/awt/Container;, r2 >, < Ljava/awt/GridLayout;, new, return value from java.awt.GridLayout.<init>()V, r3 >, < [Lorg/java_websocket/drafts/Draft;, new, 1, r4 >]
148 aload_0         [< Ljavax/swing/JButton;, 0:edu.nyu.websocket.ChatClient.close Ljavax/swing/JButton; >]::[< Ledu/nyu/websocket/ChatClient;, IP, r0 >, < Ljava/lang/String;, IP, r1 >, < Ljava/awt/Container;, return value from javax.swing.JFrame.getContentPane()Ljava/awt/Container;, r2 >, < Ljava/awt/GridLayout;, new, return value from java.awt.GridLayout.<init>()V, r3 >, < [Lorg/java_websocket/drafts/Draft;, new, 1, r4 >]
149 invokevirtual   [< Ljavax/swing/JButton;, 0:edu.nyu.websocket.ChatClient.close Ljavax/swing/JButton; >, < Ledu/nyu/websocket/ChatClient;, IP, r0 >]::[< Ledu/nyu/websocket/ChatClient;, IP, r0 >, < Ljava/lang/String;, IP, r1 >, < Ljava/awt/Container;, return value from javax.swing.JFrame.getContentPane()Ljava/awt/Container;, r2 >, < Ljava/awt/GridLayout;, new, return value from java.awt.GridLayout.<init>()V, r3 >, < [Lorg/java_websocket/drafts/Draft;, new, 1, r4 >]
152 aload_0         []::[< Ledu/nyu/websocket/ChatClient;, IP, r0 >, < Ljava/lang/String;, IP, r1 >, < Ljava/awt/Container;, return value from javax.swing.JFrame.getContentPane()Ljava/awt/Container;, r2 >, < Ljava/awt/GridLayout;, new, return value from java.awt.GridLayout.<init>()V, r3 >, < [Lorg/java_websocket/drafts/Draft;, new, 1, r4 >]
153 getfield        [< Ledu/nyu/websocket/ChatClient;, IP, r0 >]::[< Ledu/nyu/websocket/ChatClient;, IP, r0 >, < Ljava/lang/String;, IP, r1 >, < Ljava/awt/Container;, return value from javax.swing.JFrame.getContentPane()Ljava/awt/Container;, r2 >, < Ljava/awt/GridLayout;, new, return value from java.awt.GridLayout.<init>()V, r3 >, < [Lorg/java_websocket/drafts/Draft;, new, 1, r4 >]
156 iconst_0        [< Ljavax/swing/JButton;, 0:edu.nyu.websocket.ChatClient.close Ljavax/swing/JButton; >]::[< Ledu/nyu/websocket/ChatClient;, IP, r0 >, < Ljava/lang/String;, IP, r1 >, < Ljava/awt/Container;, return value from javax.swing.JFrame.getContentPane()Ljava/awt/Container;, r2 >, < Ljava/awt/GridLayout;, new, return value from java.awt.GridLayout.<init>()V, r3 >, < [Lorg/java_websocket/drafts/Draft;, new, 1, r4 >]
157 invokevirtual   [< Ljavax/swing/JButton;, 0:edu.nyu.websocket.ChatClient.close Ljavax/swing/JButton; >, < I, 0 >]::[< Ledu/nyu/websocket/ChatClient;, IP, r0 >, < Ljava/lang/String;, IP, r1 >, < Ljava/awt/Container;, return value from javax.swing.JFrame.getContentPane()Ljava/awt/Container;, r2 >, < Ljava/awt/GridLayout;, new, return value from java.awt.GridLayout.<init>()V, r3 >, < [Lorg/java_websocket/drafts/Draft;, new, 1, r4 >]
160 aload_2         []::[< Ledu/nyu/websocket/ChatClient;, IP, r0 >, < Ljava/lang/String;, IP, r1 >, < Ljava/awt/Container;, return value from javax.swing.JFrame.getContentPane()Ljava/awt/Container;, r2 >, < Ljava/awt/GridLayout;, new, return value from java.awt.GridLayout.<init>()V, r3 >, < [Lorg/java_websocket/drafts/Draft;, new, 1, r4 >]
161 aload_0         [< Ljava/awt/Container;, return value from javax.swing.JFrame.getContentPane()Ljava/awt/Container;, r2 >]::[< Ledu/nyu/websocket/ChatClient;, IP, r0 >, < Ljava/lang/String;, IP, r1 >, < Ljava/awt/Container;, return value from javax.swing.JFrame.getContentPane()Ljava/awt/Container;, r2 >, < Ljava/awt/GridLayout;, new, return value from java.awt.GridLayout.<init>()V, r3 >, < [Lorg/java_websocket/drafts/Draft;, new, 1, r4 >]
162 getfield        [< Ljava/awt/Container;, return value from javax.swing.JFrame.getContentPane()Ljava/awt/Container;, r2 >, < Ledu/nyu/websocket/ChatClient;, IP, r0 >]::[< Ledu/nyu/websocket/ChatClient;, IP, r0 >, < Ljava/lang/String;, IP, r1 >, < Ljava/awt/Container;, return value from javax.swing.JFrame.getContentPane()Ljava/awt/Container;, r2 >, < Ljava/awt/GridLayout;, new, return value from java.awt.GridLayout.<init>()V, r3 >, < [Lorg/java_websocket/drafts/Draft;, new, 1, r4 >]
165 invokevirtual   [< Ljava/awt/Container;, return value from javax.swing.JFrame.getContentPane()Ljava/awt/Container;, r2 >, < Ljavax/swing/JButton;, 0:edu.nyu.websocket.ChatClient.close Ljavax/swing/JButton; >]::[< Ledu/nyu/websocket/ChatClient;, IP, r0 >, < Ljava/lang/String;, IP, r1 >, < Ljava/awt/Container;, return value from javax.swing.JFrame.getContentPane()Ljava/awt/Container;, r2 >, < Ljava/awt/GridLayout;, new, return value from java.awt.GridLayout.<init>()V, r3 >, < [Lorg/java_websocket/drafts/Draft;, new, 1, r4 >]
168 pop             [< Ljava/awt/Component;, return value from java.awt.Container.add(Ljava/awt/Component;)Ljava/awt/Component; >]::[< Ledu/nyu/websocket/ChatClient;, IP, r0 >, < Ljava/lang/String;, IP, r1 >, < Ljava/awt/Container;, return value from javax.swing.JFrame.getContentPane()Ljava/awt/Container;, r2 >, < Ljava/awt/GridLayout;, new, return value from java.awt.GridLayout.<init>()V, r3 >, < [Lorg/java_websocket/drafts/Draft;, new, 1, r4 >]
169 new             []::[< Ledu/nyu/websocket/ChatClient;, IP, r0 >, < Ljava/lang/String;, IP, r1 >, < Ljava/awt/Container;, return value from javax.swing.JFrame.getContentPane()Ljava/awt/Container;, r2 >, < Ljava/awt/GridLayout;, new, return value from java.awt.GridLayout.<init>()V, r3 >, < [Lorg/java_websocket/drafts/Draft;, new, 1, r4 >]
172 dup             [< Ljavax/swing/JScrollPane;, new >]::[< Ledu/nyu/websocket/ChatClient;, IP, r0 >, < Ljava/lang/String;, IP, r1 >, < Ljava/awt/Container;, return value from javax.swing.JFrame.getContentPane()Ljava/awt/Container;, r2 >, < Ljava/awt/GridLayout;, new, return value from java.awt.GridLayout.<init>()V, r3 >, < [Lorg/java_websocket/drafts/Draft;, new, 1, r4 >]
173 invokespecial   [< Ljavax/swing/JScrollPane;, new >, < Ljavax/swing/JScrollPane;, new >]::[< Ledu/nyu/websocket/ChatClient;, IP, r0 >, < Ljava/lang/String;, IP, r1 >, < Ljava/awt/Container;, return value from javax.swing.JFrame.getContentPane()Ljava/awt/Container;, r2 >, < Ljava/awt/GridLayout;, new, return value from java.awt.GridLayout.<init>()V, r3 >, < [Lorg/java_websocket/drafts/Draft;, new, 1, r4 >]
176 astore          [< Ljavax/swing/JScrollPane;, new, return value from javax.swing.JScrollPane.<init>()V >]::[< Ledu/nyu/websocket/ChatClient;, IP, r0 >, < Ljava/lang/String;, IP, r1 >, < Ljava/awt/Container;, return value from javax.swing.JFrame.getContentPane()Ljava/awt/Container;, r2 >, < Ljava/awt/GridLayout;, new, return value from java.awt.GridLayout.<init>()V, r3 >, < [Lorg/java_websocket/drafts/Draft;, new, 1, r4 >]
178 aload_0         []::[< Ledu/nyu/websocket/ChatClient;, IP, r0 >, < Ljava/lang/String;, IP, r1 >, < Ljava/awt/Container;, return value from javax.swing.JFrame.getContentPane()Ljava/awt/Container;, r2 >, < Ljava/awt/GridLayout;, new, return value from java.awt.GridLayout.<init>()V, r3 >, < [Lorg/java_websocket/drafts/Draft;, new, 1, r4 >, < Ljavax/swing/JScrollPane;, new, return value from javax.swing.JScrollPane.<init>()V, r5 >]
179 new             [< Ledu/nyu/websocket/ChatClient;, IP, r0 >]::[< Ledu/nyu/websocket/ChatClient;, IP, r0 >, < Ljava/lang/String;, IP, r1 >, < Ljava/awt/Container;, return value from javax.swing.JFrame.getContentPane()Ljava/awt/Container;, r2 >, < Ljava/awt/GridLayout;, new, return value from java.awt.GridLayout.<init>()V, r3 >, < [Lorg/java_websocket/drafts/Draft;, new, 1, r4 >, < Ljavax/swing/JScrollPane;, new, return value from javax.swing.JScrollPane.<init>()V, r5 >]
182 dup             [< Ledu/nyu/websocket/ChatClient;, IP, r0 >, < Ljavax/swing/JTextArea;, new >]::[< Ledu/nyu/websocket/ChatClient;, IP, r0 >, < Ljava/lang/String;, IP, r1 >, < Ljava/awt/Container;, return value from javax.swing.JFrame.getContentPane()Ljava/awt/Container;, r2 >, < Ljava/awt/GridLayout;, new, return value from java.awt.GridLayout.<init>()V, r3 >, < [Lorg/java_websocket/drafts/Draft;, new, 1, r4 >, < Ljavax/swing/JScrollPane;, new, return value from javax.swing.JScrollPane.<init>()V, r5 >]
183 invokespecial   [< Ledu/nyu/websocket/ChatClient;, IP, r0 >, < Ljavax/swing/JTextArea;, new >, < Ljavax/swing/JTextArea;, new >]::[< Ledu/nyu/websocket/ChatClient;, IP, r0 >, < Ljava/lang/String;, IP, r1 >, < Ljava/awt/Container;, return value from javax.swing.JFrame.getContentPane()Ljava/awt/Container;, r2 >, < Ljava/awt/GridLayout;, new, return value from java.awt.GridLayout.<init>()V, r3 >, < [Lorg/java_websocket/drafts/Draft;, new, 1, r4 >, < Ljavax/swing/JScrollPane;, new, return value from javax.swing.JScrollPane.<init>()V, r5 >]
186 putfield        [< Ledu/nyu/websocket/ChatClient;, IP, r0 >, < Ljavax/swing/JTextArea;, new, return value from javax.swing.JTextArea.<init>()V >]::[< Ledu/nyu/websocket/ChatClient;, IP, r0 >, < Ljava/lang/String;, IP, r1 >, < Ljava/awt/Container;, return value from javax.swing.JFrame.getContentPane()Ljava/awt/Container;, r2 >, < Ljava/awt/GridLayout;, new, return value from java.awt.GridLayout.<init>()V, r3 >, < [Lorg/java_websocket/drafts/Draft;, new, 1, r4 >, < Ljavax/swing/JScrollPane;, new, return value from javax.swing.JScrollPane.<init>()V, r5 >]
189 aload           []::[< Ledu/nyu/websocket/ChatClient;, IP, r0 >, < Ljava/lang/String;, IP, r1 >, < Ljava/awt/Container;, return value from javax.swing.JFrame.getContentPane()Ljava/awt/Container;, r2 >, < Ljava/awt/GridLayout;, new, return value from java.awt.GridLayout.<init>()V, r3 >, < [Lorg/java_websocket/drafts/Draft;, new, 1, r4 >, < Ljavax/swing/JScrollPane;, new, return value from javax.swing.JScrollPane.<init>()V, r5 >]
191 aload_0         [< Ljavax/swing/JScrollPane;, new, return value from javax.swing.JScrollPane.<init>()V, r5 >]::[< Ledu/nyu/websocket/ChatClient;, IP, r0 >, < Ljava/lang/String;, IP, r1 >, < Ljava/awt/Container;, return value from javax.swing.JFrame.getContentPane()Ljava/awt/Container;, r2 >, < Ljava/awt/GridLayout;, new, return value from java.awt.GridLayout.<init>()V, r3 >, < [Lorg/java_websocket/drafts/Draft;, new, 1, r4 >, < Ljavax/swing/JScrollPane;, new, return value from javax.swing.JScrollPane.<init>()V, r5 >]
192 getfield        [< Ljavax/swing/JScrollPane;, new, return value from javax.swing.JScrollPane.<init>()V, r5 >, < Ledu/nyu/websocket/ChatClient;, IP, r0 >]::[< Ledu/nyu/websocket/ChatClient;, IP, r0 >, < Ljava/lang/String;, IP, r1 >, < Ljava/awt/Container;, return value from javax.swing.JFrame.getContentPane()Ljava/awt/Container;, r2 >, < Ljava/awt/GridLayout;, new, return value from java.awt.GridLayout.<init>()V, r3 >, < [Lorg/java_websocket/drafts/Draft;, new, 1, r4 >, < Ljavax/swing/JScrollPane;, new, return value from javax.swing.JScrollPane.<init>()V, r5 >]
195 invokevirtual   [< Ljavax/swing/JScrollPane;, new, return value from javax.swing.JScrollPane.<init>()V, r5 >, < Ljavax/swing/JTextArea;, 0:edu.nyu.websocket.ChatClient.ta Ljavax/swing/JTextArea; >]::[< Ledu/nyu/websocket/ChatClient;, IP, r0 >, < Ljava/lang/String;, IP, r1 >, < Ljava/awt/Container;, return value from javax.swing.JFrame.getContentPane()Ljava/awt/Container;, r2 >, < Ljava/awt/GridLayout;, new, return value from java.awt.GridLayout.<init>()V, r3 >, < [Lorg/java_websocket/drafts/Draft;, new, 1, r4 >, < Ljavax/swing/JScrollPane;, new, return value from javax.swing.JScrollPane.<init>()V, r5 >]
198 aload_2         []::[< Ledu/nyu/websocket/ChatClient;, IP, r0 >, < Ljava/lang/String;, IP, r1 >, < Ljava/awt/Container;, return value from javax.swing.JFrame.getContentPane()Ljava/awt/Container;, r2 >, < Ljava/awt/GridLayout;, new, return value from java.awt.GridLayout.<init>()V, r3 >, < [Lorg/java_websocket/drafts/Draft;, new, 1, r4 >, < Ljavax/swing/JScrollPane;, new, return value from javax.swing.JScrollPane.<init>()V, r5 >]
199 aload           [< Ljava/awt/Container;, return value from javax.swing.JFrame.getContentPane()Ljava/awt/Container;, r2 >]::[< Ledu/nyu/websocket/ChatClient;, IP, r0 >, < Ljava/lang/String;, IP, r1 >, < Ljava/awt/Container;, return value from javax.swing.JFrame.getContentPane()Ljava/awt/Container;, r2 >, < Ljava/awt/GridLayout;, new, return value from java.awt.GridLayout.<init>()V, r3 >, < [Lorg/java_websocket/drafts/Draft;, new, 1, r4 >, < Ljavax/swing/JScrollPane;, new, return value from javax.swing.JScrollPane.<init>()V, r5 >]
201 invokevirtual   [< Ljava/awt/Container;, return value from javax.swing.JFrame.getContentPane()Ljava/awt/Container;, r2 >, < Ljavax/swing/JScrollPane;, new, return value from javax.swing.JScrollPane.<init>()V, r5 >]::[< Ledu/nyu/websocket/ChatClient;, IP, r0 >, < Ljava/lang/String;, IP, r1 >, < Ljava/awt/Container;, return value from javax.swing.JFrame.getContentPane()Ljava/awt/Container;, r2 >, < Ljava/awt/GridLayout;, new, return value from java.awt.GridLayout.<init>()V, r3 >, < [Lorg/java_websocket/drafts/Draft;, new, 1, r4 >, < Ljavax/swing/JScrollPane;, new, return value from javax.swing.JScrollPane.<init>()V, r5 >]
204 pop             [< Ljava/awt/Component;, return value from java.awt.Container.add(Ljava/awt/Component;)Ljava/awt/Component; >]::[< Ledu/nyu/websocket/ChatClient;, IP, r0 >, < Ljava/lang/String;, IP, r1 >, < Ljava/awt/Container;, return value from javax.swing.JFrame.getContentPane()Ljava/awt/Container;, r2 >, < Ljava/awt/GridLayout;, new, return value from java.awt.GridLayout.<init>()V, r3 >, < [Lorg/java_websocket/drafts/Draft;, new, 1, r4 >, < Ljavax/swing/JScrollPane;, new, return value from javax.swing.JScrollPane.<init>()V, r5 >]
205 aload_0         []::[< Ledu/nyu/websocket/ChatClient;, IP, r0 >, < Ljava/lang/String;, IP, r1 >, < Ljava/awt/Container;, return value from javax.swing.JFrame.getContentPane()Ljava/awt/Container;, r2 >, < Ljava/awt/GridLayout;, new, return value from java.awt.GridLayout.<init>()V, r3 >, < [Lorg/java_websocket/drafts/Draft;, new, 1, r4 >, < Ljavax/swing/JScrollPane;, new, return value from javax.swing.JScrollPane.<init>()V, r5 >]
206 new             [< Ledu/nyu/websocket/ChatClient;, IP, r0 >]::[< Ledu/nyu/websocket/ChatClient;, IP, r0 >, < Ljava/lang/String;, IP, r1 >, < Ljava/awt/Container;, return value from javax.swing.JFrame.getContentPane()Ljava/awt/Container;, r2 >, < Ljava/awt/GridLayout;, new, return value from java.awt.GridLayout.<init>()V, r3 >, < [Lorg/java_websocket/drafts/Draft;, new, 1, r4 >, < Ljavax/swing/JScrollPane;, new, return value from javax.swing.JScrollPane.<init>()V, r5 >]
209 dup             [< Ledu/nyu/websocket/ChatClient;, IP, r0 >, < Ljavax/swing/JTextField;, new >]::[< Ledu/nyu/websocket/ChatClient;, IP, r0 >, < Ljava/lang/String;, IP, r1 >, < Ljava/awt/Container;, return value from javax.swing.JFrame.getContentPane()Ljava/awt/Container;, r2 >, < Ljava/awt/GridLayout;, new, return value from java.awt.GridLayout.<init>()V, r3 >, < [Lorg/java_websocket/drafts/Draft;, new, 1, r4 >, < Ljavax/swing/JScrollPane;, new, return value from javax.swing.JScrollPane.<init>()V, r5 >]
210 invokespecial   [< Ledu/nyu/websocket/ChatClient;, IP, r0 >, < Ljavax/swing/JTextField;, new >, < Ljavax/swing/JTextField;, new >]::[< Ledu/nyu/websocket/ChatClient;, IP, r0 >, < Ljava/lang/String;, IP, r1 >, < Ljava/awt/Container;, return value from javax.swing.JFrame.getContentPane()Ljava/awt/Container;, r2 >, < Ljava/awt/GridLayout;, new, return value from java.awt.GridLayout.<init>()V, r3 >, < [Lorg/java_websocket/drafts/Draft;, new, 1, r4 >, < Ljavax/swing/JScrollPane;, new, return value from javax.swing.JScrollPane.<init>()V, r5 >]
213 putfield        [< Ledu/nyu/websocket/ChatClient;, IP, r0 >, < Ljavax/swing/JTextField;, new, return value from javax.swing.JTextField.<init>()V >]::[< Ledu/nyu/websocket/ChatClient;, IP, r0 >, < Ljava/lang/String;, IP, r1 >, < Ljava/awt/Container;, return value from javax.swing.JFrame.getContentPane()Ljava/awt/Container;, r2 >, < Ljava/awt/GridLayout;, new, return value from java.awt.GridLayout.<init>()V, r3 >, < [Lorg/java_websocket/drafts/Draft;, new, 1, r4 >, < Ljavax/swing/JScrollPane;, new, return value from javax.swing.JScrollPane.<init>()V, r5 >]
216 aload_0         []::[< Ledu/nyu/websocket/ChatClient;, IP, r0 >, < Ljava/lang/String;, IP, r1 >, < Ljava/awt/Container;, return value from javax.swing.JFrame.getContentPane()Ljava/awt/Container;, r2 >, < Ljava/awt/GridLayout;, new, return value from java.awt.GridLayout.<init>()V, r3 >, < [Lorg/java_websocket/drafts/Draft;, new, 1, r4 >, < Ljavax/swing/JScrollPane;, new, return value from javax.swing.JScrollPane.<init>()V, r5 >]
217 getfield        [< Ledu/nyu/websocket/ChatClient;, IP, r0 >]::[< Ledu/nyu/websocket/ChatClient;, IP, r0 >, < Ljava/lang/String;, IP, r1 >, < Ljava/awt/Container;, return value from javax.swing.JFrame.getContentPane()Ljava/awt/Container;, r2 >, < Ljava/awt/GridLayout;, new, return value from java.awt.GridLayout.<init>()V, r3 >, < [Lorg/java_websocket/drafts/Draft;, new, 1, r4 >, < Ljavax/swing/JScrollPane;, new, return value from javax.swing.JScrollPane.<init>()V, r5 >]
220 ldc             [< Ljavax/swing/JTextField;, 0:edu.nyu.websocket.ChatClient.chatField Ljavax/swing/JTextField; >]::[< Ledu/nyu/websocket/ChatClient;, IP, r0 >, < Ljava/lang/String;, IP, r1 >, < Ljava/awt/Container;, return value from javax.swing.JFrame.getContentPane()Ljava/awt/Container;, r2 >, < Ljava/awt/GridLayout;, new, return value from java.awt.GridLayout.<init>()V, r3 >, < [Lorg/java_websocket/drafts/Draft;, new, 1, r4 >, < Ljavax/swing/JScrollPane;, new, return value from javax.swing.JScrollPane.<init>()V, r5 >]
222 invokevirtual   [< Ljavax/swing/JTextField;, 0:edu.nyu.websocket.ChatClient.chatField Ljavax/swing/JTextField; >, < Ljava/lang/String;, "" >]::[< Ledu/nyu/websocket/ChatClient;, IP, r0 >, < Ljava/lang/String;, IP, r1 >, < Ljava/awt/Container;, return value from javax.swing.JFrame.getContentPane()Ljava/awt/Container;, r2 >, < Ljava/awt/GridLayout;, new, return value from java.awt.GridLayout.<init>()V, r3 >, < [Lorg/java_websocket/drafts/Draft;, new, 1, r4 >, < Ljavax/swing/JScrollPane;, new, return value from javax.swing.JScrollPane.<init>()V, r5 >]
225 aload_0         []::[< Ledu/nyu/websocket/ChatClient;, IP, r0 >, < Ljava/lang/String;, IP, r1 >, < Ljava/awt/Container;, return value from javax.swing.JFrame.getContentPane()Ljava/awt/Container;, r2 >, < Ljava/awt/GridLayout;, new, return value from java.awt.GridLayout.<init>()V, r3 >, < [Lorg/java_websocket/drafts/Draft;, new, 1, r4 >, < Ljavax/swing/JScrollPane;, new, return value from javax.swing.JScrollPane.<init>()V, r5 >]
226 getfield        [< Ledu/nyu/websocket/ChatClient;, IP, r0 >]::[< Ledu/nyu/websocket/ChatClient;, IP, r0 >, < Ljava/lang/String;, IP, r1 >, < Ljava/awt/Container;, return value from javax.swing.JFrame.getContentPane()Ljava/awt/Container;, r2 >, < Ljava/awt/GridLayout;, new, return value from java.awt.GridLayout.<init>()V, r3 >, < [Lorg/java_websocket/drafts/Draft;, new, 1, r4 >, < Ljavax/swing/JScrollPane;, new, return value from javax.swing.JScrollPane.<init>()V, r5 >]
229 aload_0         [< Ljavax/swing/JTextField;, 0:edu.nyu.websocket.ChatClient.chatField Ljavax/swing/JTextField; >]::[< Ledu/nyu/websocket/ChatClient;, IP, r0 >, < Ljava/lang/String;, IP, r1 >, < Ljava/awt/Container;, return value from javax.swing.JFrame.getContentPane()Ljava/awt/Container;, r2 >, < Ljava/awt/GridLayout;, new, return value from java.awt.GridLayout.<init>()V, r3 >, < [Lorg/java_websocket/drafts/Draft;, new, 1, r4 >, < Ljavax/swing/JScrollPane;, new, return value from javax.swing.JScrollPane.<init>()V, r5 >]
230 invokevirtual   [< Ljavax/swing/JTextField;, 0:edu.nyu.websocket.ChatClient.chatField Ljavax/swing/JTextField; >, < Ledu/nyu/websocket/ChatClient;, IP, r0 >]::[< Ledu/nyu/websocket/ChatClient;, IP, r0 >, < Ljava/lang/String;, IP, r1 >, < Ljava/awt/Container;, return value from javax.swing.JFrame.getContentPane()Ljava/awt/Container;, r2 >, < Ljava/awt/GridLayout;, new, return value from java.awt.GridLayout.<init>()V, r3 >, < [Lorg/java_websocket/drafts/Draft;, new, 1, r4 >, < Ljavax/swing/JScrollPane;, new, return value from javax.swing.JScrollPane.<init>()V, r5 >]
233 aload_2         []::[< Ledu/nyu/websocket/ChatClient;, IP, r0 >, < Ljava/lang/String;, IP, r1 >, < Ljava/awt/Container;, return value from javax.swing.JFrame.getContentPane()Ljava/awt/Container;, r2 >, < Ljava/awt/GridLayout;, new, return value from java.awt.GridLayout.<init>()V, r3 >, < [Lorg/java_websocket/drafts/Draft;, new, 1, r4 >, < Ljavax/swing/JScrollPane;, new, return value from javax.swing.JScrollPane.<init>()V, r5 >]
234 aload_0         [< Ljava/awt/Container;, return value from javax.swing.JFrame.getContentPane()Ljava/awt/Container;, r2 >]::[< Ledu/nyu/websocket/ChatClient;, IP, r0 >, < Ljava/lang/String;, IP, r1 >, < Ljava/awt/Container;, return value from javax.swing.JFrame.getContentPane()Ljava/awt/Container;, r2 >, < Ljava/awt/GridLayout;, new, return value from java.awt.GridLayout.<init>()V, r3 >, < [Lorg/java_websocket/drafts/Draft;, new, 1, r4 >, < Ljavax/swing/JScrollPane;, new, return value from javax.swing.JScrollPane.<init>()V, r5 >]
235 getfield        [< Ljava/awt/Container;, return value from javax.swing.JFrame.getContentPane()Ljava/awt/Container;, r2 >, < Ledu/nyu/websocket/ChatClient;, IP, r0 >]::[< Ledu/nyu/websocket/ChatClient;, IP, r0 >, < Ljava/lang/String;, IP, r1 >, < Ljava/awt/Container;, return value from javax.swing.JFrame.getContentPane()Ljava/awt/Container;, r2 >, < Ljava/awt/GridLayout;, new, return value from java.awt.GridLayout.<init>()V, r3 >, < [Lorg/java_websocket/drafts/Draft;, new, 1, r4 >, < Ljavax/swing/JScrollPane;, new, return value from javax.swing.JScrollPane.<init>()V, r5 >]
238 invokevirtual   [< Ljava/awt/Container;, return value from javax.swing.JFrame.getContentPane()Ljava/awt/Container;, r2 >, < Ljavax/swing/JTextField;, 0:edu.nyu.websocket.ChatClient.chatField Ljavax/swing/JTextField; >]::[< Ledu/nyu/websocket/ChatClient;, IP, r0 >, < Ljava/lang/String;, IP, r1 >, < Ljava/awt/Container;, return value from javax.swing.JFrame.getContentPane()Ljava/awt/Container;, r2 >, < Ljava/awt/GridLayout;, new, return value from java.awt.GridLayout.<init>()V, r3 >, < [Lorg/java_websocket/drafts/Draft;, new, 1, r4 >, < Ljavax/swing/JScrollPane;, new, return value from javax.swing.JScrollPane.<init>()V, r5 >]
241 pop             [< Ljava/awt/Component;, return value from java.awt.Container.add(Ljava/awt/Component;)Ljava/awt/Component; >]::[< Ledu/nyu/websocket/ChatClient;, IP, r0 >, < Ljava/lang/String;, IP, r1 >, < Ljava/awt/Container;, return value from javax.swing.JFrame.getContentPane()Ljava/awt/Container;, r2 >, < Ljava/awt/GridLayout;, new, return value from java.awt.GridLayout.<init>()V, r3 >, < [Lorg/java_websocket/drafts/Draft;, new, 1, r4 >, < Ljavax/swing/JScrollPane;, new, return value from javax.swing.JScrollPane.<init>()V, r5 >]
242 new             []::[< Ledu/nyu/websocket/ChatClient;, IP, r0 >, < Ljava/lang/String;, IP, r1 >, < Ljava/awt/Container;, return value from javax.swing.JFrame.getContentPane()Ljava/awt/Container;, r2 >, < Ljava/awt/GridLayout;, new, return value from java.awt.GridLayout.<init>()V, r3 >, < [Lorg/java_websocket/drafts/Draft;, new, 1, r4 >, < Ljavax/swing/JScrollPane;, new, return value from javax.swing.JScrollPane.<init>()V, r5 >]
245 dup             [< Ljava/awt/Dimension;, new >]::[< Ledu/nyu/websocket/ChatClient;, IP, r0 >, < Ljava/lang/String;, IP, r1 >, < Ljava/awt/Container;, return value from javax.swing.JFrame.getContentPane()Ljava/awt/Container;, r2 >, < Ljava/awt/GridLayout;, new, return value from java.awt.GridLayout.<init>()V, r3 >, < [Lorg/java_websocket/drafts/Draft;, new, 1, r4 >, < Ljavax/swing/JScrollPane;, new, return value from javax.swing.JScrollPane.<init>()V, r5 >]
246 sipush          [< Ljava/awt/Dimension;, new >, < Ljava/awt/Dimension;, new >]::[< Ledu/nyu/websocket/ChatClient;, IP, r0 >, < Ljava/lang/String;, IP, r1 >, < Ljava/awt/Container;, return value from javax.swing.JFrame.getContentPane()Ljava/awt/Container;, r2 >, < Ljava/awt/GridLayout;, new, return value from java.awt.GridLayout.<init>()V, r3 >, < [Lorg/java_websocket/drafts/Draft;, new, 1, r4 >, < Ljavax/swing/JScrollPane;, new, return value from javax.swing.JScrollPane.<init>()V, r5 >]
249 sipush          [< Ljava/awt/Dimension;, new >, < Ljava/awt/Dimension;, new >, < I, 300 >]::[< Ledu/nyu/websocket/ChatClient;, IP, r0 >, < Ljava/lang/String;, IP, r1 >, < Ljava/awt/Container;, return value from javax.swing.JFrame.getContentPane()Ljava/awt/Container;, r2 >, < Ljava/awt/GridLayout;, new, return value from java.awt.GridLayout.<init>()V, r3 >, < [Lorg/java_websocket/drafts/Draft;, new, 1, r4 >, < Ljavax/swing/JScrollPane;, new, return value from javax.swing.JScrollPane.<init>()V, r5 >]
252 invokespecial   [< Ljava/awt/Dimension;, new >, < Ljava/awt/Dimension;, new >, < I, 300 >, < I, 400 >]::[< Ledu/nyu/websocket/ChatClient;, IP, r0 >, < Ljava/lang/String;, IP, r1 >, < Ljava/awt/Container;, return value from javax.swing.JFrame.getContentPane()Ljava/awt/Container;, r2 >, < Ljava/awt/GridLayout;, new, return value from java.awt.GridLayout.<init>()V, r3 >, < [Lorg/java_websocket/drafts/Draft;, new, 1, r4 >, < Ljavax/swing/JScrollPane;, new, return value from javax.swing.JScrollPane.<init>()V, r5 >]
255 astore          [< Ljava/awt/Dimension;, new, return value from java.awt.Dimension.<init>(II)V >]::[< Ledu/nyu/websocket/ChatClient;, IP, r0 >, < Ljava/lang/String;, IP, r1 >, < Ljava/awt/Container;, return value from javax.swing.JFrame.getContentPane()Ljava/awt/Container;, r2 >, < Ljava/awt/GridLayout;, new, return value from java.awt.GridLayout.<init>()V, r3 >, < [Lorg/java_websocket/drafts/Draft;, new, 1, r4 >, < Ljavax/swing/JScrollPane;, new, return value from javax.swing.JScrollPane.<init>()V, r5 >]
257 aload_0         []::[< Ledu/nyu/websocket/ChatClient;, IP, r0 >, < Ljava/lang/String;, IP, r1 >, < Ljava/awt/Container;, return value from javax.swing.JFrame.getContentPane()Ljava/awt/Container;, r2 >, < Ljava/awt/GridLayout;, new, return value from java.awt.GridLayout.<init>()V, r3 >, < [Lorg/java_websocket/drafts/Draft;, new, 1, r4 >, < Ljavax/swing/JScrollPane;, new, return value from javax.swing.JScrollPane.<init>()V, r5 >, < Ljava/awt/Dimension;, new, return value from java.awt.Dimension.<init>(II)V, r6 >]
258 aload           [< Ledu/nyu/websocket/ChatClient;, IP, r0 >]::[< Ledu/nyu/websocket/ChatClient;, IP, r0 >, < Ljava/lang/String;, IP, r1 >, < Ljava/awt/Container;, return value from javax.swing.JFrame.getContentPane()Ljava/awt/Container;, r2 >, < Ljava/awt/GridLayout;, new, return value from java.awt.GridLayout.<init>()V, r3 >, < [Lorg/java_websocket/drafts/Draft;, new, 1, r4 >, < Ljavax/swing/JScrollPane;, new, return value from javax.swing.JScrollPane.<init>()V, r5 >, < Ljava/awt/Dimension;, new, return value from java.awt.Dimension.<init>(II)V, r6 >]
260 invokevirtual   [< Ledu/nyu/websocket/ChatClient;, IP, r0 >, < Ljava/awt/Dimension;, new, return value from java.awt.Dimension.<init>(II)V, r6 >]::[< Ledu/nyu/websocket/ChatClient;, IP, r0 >, < Ljava/lang/String;, IP, r1 >, < Ljava/awt/Container;, return value from javax.swing.JFrame.getContentPane()Ljava/awt/Container;, r2 >, < Ljava/awt/GridLayout;, new, return value from java.awt.GridLayout.<init>()V, r3 >, < [Lorg/java_websocket/drafts/Draft;, new, 1, r4 >, < Ljavax/swing/JScrollPane;, new, return value from javax.swing.JScrollPane.<init>()V, r5 >, < Ljava/awt/Dimension;, new, return value from java.awt.Dimension.<init>(II)V, r6 >]
263 aload_0         []::[< Ledu/nyu/websocket/ChatClient;, IP, r0 >, < Ljava/lang/String;, IP, r1 >, < Ljava/awt/Container;, return value from javax.swing.JFrame.getContentPane()Ljava/awt/Container;, r2 >, < Ljava/awt/GridLayout;, new, return value from java.awt.GridLayout.<init>()V, r3 >, < [Lorg/java_websocket/drafts/Draft;, new, 1, r4 >, < Ljavax/swing/JScrollPane;, new, return value from javax.swing.JScrollPane.<init>()V, r5 >, < Ljava/awt/Dimension;, new, return value from java.awt.Dimension.<init>(II)V, r6 >]
264 aload           [< Ledu/nyu/websocket/ChatClient;, IP, r0 >]::[< Ledu/nyu/websocket/ChatClient;, IP, r0 >, < Ljava/lang/String;, IP, r1 >, < Ljava/awt/Container;, return value from javax.swing.JFrame.getContentPane()Ljava/awt/Container;, r2 >, < Ljava/awt/GridLayout;, new, return value from java.awt.GridLayout.<init>()V, r3 >, < [Lorg/java_websocket/drafts/Draft;, new, 1, r4 >, < Ljavax/swing/JScrollPane;, new, return value from javax.swing.JScrollPane.<init>()V, r5 >, < Ljava/awt/Dimension;, new, return value from java.awt.Dimension.<init>(II)V, r6 >]
266 invokevirtual   [< Ledu/nyu/websocket/ChatClient;, IP, r0 >, < Ljava/awt/Dimension;, new, return value from java.awt.Dimension.<init>(II)V, r6 >]::[< Ledu/nyu/websocket/ChatClient;, IP, r0 >, < Ljava/lang/String;, IP, r1 >, < Ljava/awt/Container;, return value from javax.swing.JFrame.getContentPane()Ljava/awt/Container;, r2 >, < Ljava/awt/GridLayout;, new, return value from java.awt.GridLayout.<init>()V, r3 >, < [Lorg/java_websocket/drafts/Draft;, new, 1, r4 >, < Ljavax/swing/JScrollPane;, new, return value from javax.swing.JScrollPane.<init>()V, r5 >, < Ljava/awt/Dimension;, new, return value from java.awt.Dimension.<init>(II)V, r6 >]
269 aload_0         []::[< Ledu/nyu/websocket/ChatClient;, IP, r0 >, < Ljava/lang/String;, IP, r1 >, < Ljava/awt/Container;, return value from javax.swing.JFrame.getContentPane()Ljava/awt/Container;, r2 >, < Ljava/awt/GridLayout;, new, return value from java.awt.GridLayout.<init>()V, r3 >, < [Lorg/java_websocket/drafts/Draft;, new, 1, r4 >, < Ljavax/swing/JScrollPane;, new, return value from javax.swing.JScrollPane.<init>()V, r5 >, < Ljava/awt/Dimension;, new, return value from java.awt.Dimension.<init>(II)V, r6 >]
270 new             [< Ledu/nyu/websocket/ChatClient;, IP, r0 >]::[< Ledu/nyu/websocket/ChatClient;, IP, r0 >, < Ljava/lang/String;, IP, r1 >, < Ljava/awt/Container;, return value from javax.swing.JFrame.getContentPane()Ljava/awt/Container;, r2 >, < Ljava/awt/GridLayout;, new, return value from java.awt.GridLayout.<init>()V, r3 >, < [Lorg/java_websocket/drafts/Draft;, new, 1, r4 >, < Ljavax/swing/JScrollPane;, new, return value from javax.swing.JScrollPane.<init>()V, r5 >, < Ljava/awt/Dimension;, new, return value from java.awt.Dimension.<init>(II)V, r6 >]
273 dup             [< Ledu/nyu/websocket/ChatClient;, IP, r0 >, < Ledu/nyu/websocket/ChatClient$1;, new >]::[< Ledu/nyu/websocket/ChatClient;, IP, r0 >, < Ljava/lang/String;, IP, r1 >, < Ljava/awt/Container;, return value from javax.swing.JFrame.getContentPane()Ljava/awt/Container;, r2 >, < Ljava/awt/GridLayout;, new, return value from java.awt.GridLayout.<init>()V, r3 >, < [Lorg/java_websocket/drafts/Draft;, new, 1, r4 >, < Ljavax/swing/JScrollPane;, new, return value from javax.swing.JScrollPane.<init>()V, r5 >, < Ljava/awt/Dimension;, new, return value from java.awt.Dimension.<init>(II)V, r6 >]
274 aload_0         [< Ledu/nyu/websocket/ChatClient;, IP, r0 >, < Ledu/nyu/websocket/ChatClient$1;, new >, < Ledu/nyu/websocket/ChatClient$1;, new >]::[< Ledu/nyu/websocket/ChatClient;, IP, r0 >, < Ljava/lang/String;, IP, r1 >, < Ljava/awt/Container;, return value from javax.swing.JFrame.getContentPane()Ljava/awt/Container;, r2 >, < Ljava/awt/GridLayout;, new, return value from java.awt.GridLayout.<init>()V, r3 >, < [Lorg/java_websocket/drafts/Draft;, new, 1, r4 >, < Ljavax/swing/JScrollPane;, new, return value from javax.swing.JScrollPane.<init>()V, r5 >, < Ljava/awt/Dimension;, new, return value from java.awt.Dimension.<init>(II)V, r6 >]
275 invokespecial   [< Ledu/nyu/websocket/ChatClient;, IP, r0 >, < Ledu/nyu/websocket/ChatClient$1;, new >, < Ledu/nyu/websocket/ChatClient$1;, new >, < Ledu/nyu/websocket/ChatClient;, IP, r0 >]::[< Ledu/nyu/websocket/ChatClient;, IP, r0 >, < Ljava/lang/String;, IP, r1 >, < Ljava/awt/Container;, return value from javax.swing.JFrame.getContentPane()Ljava/awt/Container;, r2 >, < Ljava/awt/GridLayout;, new, return value from java.awt.GridLayout.<init>()V, r3 >, < [Lorg/java_websocket/drafts/Draft;, new, 1, r4 >, < Ljavax/swing/JScrollPane;, new, return value from javax.swing.JScrollPane.<init>()V, r5 >, < Ljava/awt/Dimension;, new, return value from java.awt.Dimension.<init>(II)V, r6 >]
278 invokevirtual   [< Ledu/nyu/websocket/ChatClient;, IP, r0 >, < Ledu/nyu/websocket/ChatClient$1;, new, return value from edu.nyu.websocket.ChatClient$1.<init>(edu.nyu.websocket.ChatClient) >]::[< Ledu/nyu/websocket/ChatClient;, IP, r0 >, < Ljava/lang/String;, IP, r1 >, < Ljava/awt/Container;, return value from javax.swing.JFrame.getContentPane()Ljava/awt/Container;, r2 >, < Ljava/awt/GridLayout;, new, return value from java.awt.GridLayout.<init>()V, r3 >, < [Lorg/java_websocket/drafts/Draft;, new, 1, r4 >, < Ljavax/swing/JScrollPane;, new, return value from javax.swing.JScrollPane.<init>()V, r5 >, < Ljava/awt/Dimension;, new, return value from java.awt.Dimension.<init>(II)V, r6 >]
281 aload_0         []::[< Ledu/nyu/websocket/ChatClient;, IP, r0 >, < Ljava/lang/String;, IP, r1 >, < Ljava/awt/Container;, return value from javax.swing.JFrame.getContentPane()Ljava/awt/Container;, r2 >, < Ljava/awt/GridLayout;, new, return value from java.awt.GridLayout.<init>()V, r3 >, < [Lorg/java_websocket/drafts/Draft;, new, 1, r4 >, < Ljavax/swing/JScrollPane;, new, return value from javax.swing.JScrollPane.<init>()V, r5 >, < Ljava/awt/Dimension;, new, return value from java.awt.Dimension.<init>(II)V, r6 >]
282 aconst_null     [< Ledu/nyu/websocket/ChatClient;, IP, r0 >]::[< Ledu/nyu/websocket/ChatClient;, IP, r0 >, < Ljava/lang/String;, IP, r1 >, < Ljava/awt/Container;, return value from javax.swing.JFrame.getContentPane()Ljava/awt/Container;, r2 >, < Ljava/awt/GridLayout;, new, return value from java.awt.GridLayout.<init>()V, r3 >, < [Lorg/java_websocket/drafts/Draft;, new, 1, r4 >, < Ljavax/swing/JScrollPane;, new, return value from javax.swing.JScrollPane.<init>()V, r5 >, < Ljava/awt/Dimension;, new, return value from java.awt.Dimension.<init>(II)V, r6 >]
283 invokevirtual   [< Ledu/nyu/websocket/ChatClient;, IP, r0 >, < Ljava/lang/Object;, isNull >]::[< Ledu/nyu/websocket/ChatClient;, IP, r0 >, < Ljava/lang/String;, IP, r1 >, < Ljava/awt/Container;, return value from javax.swing.JFrame.getContentPane()Ljava/awt/Container;, r2 >, < Ljava/awt/GridLayout;, new, return value from java.awt.GridLayout.<init>()V, r3 >, < [Lorg/java_websocket/drafts/Draft;, new, 1, r4 >, < Ljavax/swing/JScrollPane;, new, return value from javax.swing.JScrollPane.<init>()V, r5 >, < Ljava/awt/Dimension;, new, return value from java.awt.Dimension.<init>(II)V, r6 >]
286 aload_0         []::[< Ledu/nyu/websocket/ChatClient;, IP, r0 >, < Ljava/lang/String;, IP, r1 >, < Ljava/awt/Container;, return value from javax.swing.JFrame.getContentPane()Ljava/awt/Container;, r2 >, < Ljava/awt/GridLayout;, new, return value from java.awt.GridLayout.<init>()V, r3 >, < [Lorg/java_websocket/drafts/Draft;, new, 1, r4 >, < Ljavax/swing/JScrollPane;, new, return value from javax.swing.JScrollPane.<init>()V, r5 >, < Ljava/awt/Dimension;, new, return value from java.awt.Dimension.<init>(II)V, r6 >]
287 iconst_1        [< Ledu/nyu/websocket/ChatClient;, IP, r0 >]::[< Ledu/nyu/websocket/ChatClient;, IP, r0 >, < Ljava/lang/String;, IP, r1 >, < Ljava/awt/Container;, return value from javax.swing.JFrame.getContentPane()Ljava/awt/Container;, r2 >, < Ljava/awt/GridLayout;, new, return value from java.awt.GridLayout.<init>()V, r3 >, < [Lorg/java_websocket/drafts/Draft;, new, 1, r4 >, < Ljavax/swing/JScrollPane;, new, return value from javax.swing.JScrollPane.<init>()V, r5 >, < Ljava/awt/Dimension;, new, return value from java.awt.Dimension.<init>(II)V, r6 >]
288 invokevirtual   [< Ledu/nyu/websocket/ChatClient;, IP, r0 >, < I, 1 >]::[< Ledu/nyu/websocket/ChatClient;, IP, r0 >, < Ljava/lang/String;, IP, r1 >, < Ljava/awt/Container;, return value from javax.swing.JFrame.getContentPane()Ljava/awt/Container;, r2 >, < Ljava/awt/GridLayout;, new, return value from java.awt.GridLayout.<init>()V, r3 >, < [Lorg/java_websocket/drafts/Draft;, new, 1, r4 >, < Ljavax/swing/JScrollPane;, new, return value from javax.swing.JScrollPane.<init>()V, r5 >, < Ljava/awt/Dimension;, new, return value from java.awt.Dimension.<init>(II)V, r6 >]
291 return          []::[< Ledu/nyu/websocket/ChatClient;, IP, r0 >, < Ljava/lang/String;, IP, r1 >, < Ljava/awt/Container;, return value from javax.swing.JFrame.getContentPane()Ljava/awt/Container;, r2 >, < Ljava/awt/GridLayout;, new, return value from java.awt.GridLayout.<init>()V, r3 >, < [Lorg/java_websocket/drafts/Draft;, new, 1, r4 >, < Ljavax/swing/JScrollPane;, new, return value from javax.swing.JScrollPane.<init>()V, r5 >, < Ljava/awt/Dimension;, new, return value from java.awt.Dimension.<init>(II)V, r6 >]

edu.nyu.websocket.ChatClient.actionPerformed : (Ljava.awt.event.ActionEvent;)V
  0 aload_1         []::[< Ledu/nyu/websocket/ChatClient;, IP, r0 >, < Ljava/awt/event/ActionEvent;, IP, r1 >]
  1 invokevirtual   [< Ljava/awt/event/ActionEvent;, IP, r1 >]::[< Ledu/nyu/websocket/ChatClient;, IP, r0 >, < Ljava/awt/event/ActionEvent;, IP, r1 >]
  4 aload_0         [< Ljava/lang/Object;, return value from java.awt.AWTEvent.getSource() >]::[< Ledu/nyu/websocket/ChatClient;, IP, r0 >, < Ljava/awt/event/ActionEvent;, IP, r1 >]
  5 getfield        [< Ljava/lang/Object;, return value from java.awt.AWTEvent.getSource() >, < Ledu/nyu/websocket/ChatClient;, IP, r0 >]::[< Ledu/nyu/websocket/ChatClient;, IP, r0 >, < Ljava/awt/event/ActionEvent;, IP, r1 >]
  8 if_acmpne       [< Ljava/lang/Object;, return value from java.awt.AWTEvent.getSource() >, < Ljavax/swing/JTextField;, 0:edu.nyu.websocket.ChatClient.chatField Ljavax/swing/JTextField; >]::[< Ledu/nyu/websocket/ChatClient;, IP, r0 >, < Ljava/awt/event/ActionEvent;, IP, r1 >]
 11 aload_0         []::[< Ledu/nyu/websocket/ChatClient;, IP, r0 >, < Ljava/awt/event/ActionEvent;, IP, r1 >]
 12 getfield        [< Ledu/nyu/websocket/ChatClient;, IP, r0 >]::[< Ledu/nyu/websocket/ChatClient;, IP, r0 >, < Ljava/awt/event/ActionEvent;, IP, r1 >]
 15 ifnull          [< Ledu/nyu/websocket/ChatClient$2;, 0:edu.nyu.websocket.ChatClient.cc Lorg/java_websocket/client/WebSocketClient; >]::[< Ledu/nyu/websocket/ChatClient;, IP, r0 >, < Ljava/awt/event/ActionEvent;, IP, r1 >]
 18 aload_0         []::[< Ledu/nyu/websocket/ChatClient;, IP, r0 >, < Ljava/awt/event/ActionEvent;, IP, r1 >]
 19 getfield        [< Ledu/nyu/websocket/ChatClient;, IP, r0 >]::[< Ledu/nyu/websocket/ChatClient;, IP, r0 >, < Ljava/awt/event/ActionEvent;, IP, r1 >]
 22 aload_0         [< Ledu/nyu/websocket/ChatClient$2;, 0:edu.nyu.websocket.ChatClient.cc Lorg/java_websocket/client/WebSocketClient; >]::[< Ledu/nyu/websocket/ChatClient;, IP, r0 >, < Ljava/awt/event/ActionEvent;, IP, r1 >]
 23 getfield        [< Ledu/nyu/websocket/ChatClient$2;, 0:edu.nyu.websocket.ChatClient.cc Lorg/java_websocket/client/WebSocketClient; >, < Ledu/nyu/websocket/ChatClient;, IP, r0 >]::[< Ledu/nyu/websocket/ChatClient;, IP, r0 >, < Ljava/awt/event/ActionEvent;, IP, r1 >]
 26 invokevirtual   [< Ledu/nyu/websocket/ChatClient$2;, 0:edu.nyu.websocket.ChatClient.cc Lorg/java_websocket/client/WebSocketClient; >, < Ljavax/swing/JTextField;, 0:edu.nyu.websocket.ChatClient.chatField Ljavax/swing/JTextField; >]::[< Ledu/nyu/websocket/ChatClient;, IP, r0 >, < Ljava/awt/event/ActionEvent;, IP, r1 >]
 29 invokevirtual   [< Ledu/nyu/websocket/ChatClient$2;, 0:edu.nyu.websocket.ChatClient.cc Lorg/java_websocket/client/WebSocketClient; >, < Ljava/lang/String;, return value from javax.swing.JTextField.getText() >]::[< Ledu/nyu/websocket/ChatClient;, IP, r0 >, < Ljava/awt/event/ActionEvent;, IP, r1 >]
 32 aload_0         []::[< Ledu/nyu/websocket/ChatClient;, IP, r0 >, < Ljava/awt/event/ActionEvent;, IP, r1 >]
 33 getfield        [< Ledu/nyu/websocket/ChatClient;, IP, r0 >]::[< Ledu/nyu/websocket/ChatClient;, IP, r0 >, < Ljava/awt/event/ActionEvent;, IP, r1 >]
 36 ldc             [< Ljavax/swing/JTextField;, 0:edu.nyu.websocket.ChatClient.chatField Ljavax/swing/JTextField; >]::[< Ledu/nyu/websocket/ChatClient;, IP, r0 >, < Ljava/awt/event/ActionEvent;, IP, r1 >]
 38 invokevirtual   [< Ljavax/swing/JTextField;, 0:edu.nyu.websocket.ChatClient.chatField Ljavax/swing/JTextField; >, < Ljava/lang/String;, "" >]::[< Ledu/nyu/websocket/ChatClient;, IP, r0 >, < Ljava/awt/event/ActionEvent;, IP, r1 >]
 41 aload_0         []::[< Ledu/nyu/websocket/ChatClient;, IP, r0 >, < Ljava/awt/event/ActionEvent;, IP, r1 >]
 42 getfield        [< Ledu/nyu/websocket/ChatClient;, IP, r0 >]::[< Ledu/nyu/websocket/ChatClient;, IP, r0 >, < Ljava/awt/event/ActionEvent;, IP, r1 >]
 45 invokevirtual   [< Ljavax/swing/JTextField;, 0:edu.nyu.websocket.ChatClient.chatField Ljavax/swing/JTextField; >]::[< Ledu/nyu/websocket/ChatClient;, IP, r0 >, < Ljava/awt/event/ActionEvent;, IP, r1 >]
 48 goto            []::[< Ledu/nyu/websocket/ChatClient;, IP, r0 >, < Ljava/awt/event/ActionEvent;, IP, r1 >]
 51 aload_1         []::[< Ledu/nyu/websocket/ChatClient;, IP, r0 >, < Ljava/awt/event/ActionEvent;, IP, r1 >]
 52 invokevirtual   [< Ljava/awt/event/ActionEvent;, IP, r1 >]::[< Ledu/nyu/websocket/ChatClient;, IP, r0 >, < Ljava/awt/event/ActionEvent;, IP, r1 >]
 55 aload_0         [< Ljava/lang/Object;, return value from java.awt.AWTEvent.getSource() >]::[< Ledu/nyu/websocket/ChatClient;, IP, r0 >, < Ljava/awt/event/ActionEvent;, IP, r1 >]
 56 getfield        [< Ljava/lang/Object;, return value from java.awt.AWTEvent.getSource() >, < Ledu/nyu/websocket/ChatClient;, IP, r0 >]::[< Ledu/nyu/websocket/ChatClient;, IP, r0 >, < Ljava/awt/event/ActionEvent;, IP, r1 >]
 59 if_acmpne       [< Ljava/lang/Object;, return value from java.awt.AWTEvent.getSource() >, < Ljavax/swing/JButton;, 0:edu.nyu.websocket.ChatClient.connect Ljavax/swing/JButton; >]::[< Ledu/nyu/websocket/ChatClient;, IP, r0 >, < Ljava/awt/event/ActionEvent;, IP, r1 >]
 62 aload_0         []::[< Ledu/nyu/websocket/ChatClient;, IP, r0 >, < Ljava/awt/event/ActionEvent;, IP, r1 >]
 63 new             [< Ledu/nyu/websocket/ChatClient;, IP, r0 >]::[< Ledu/nyu/websocket/ChatClient;, IP, r0 >, < Ljava/awt/event/ActionEvent;, IP, r1 >]
 66 dup             [< Ledu/nyu/websocket/ChatClient;, IP, r0 >, < Ledu/nyu/websocket/ChatClient$2;, new >]::[< Ledu/nyu/websocket/ChatClient;, IP, r0 >, < Ljava/awt/event/ActionEvent;, IP, r1 >]
 67 aload_0         [< Ledu/nyu/websocket/ChatClient;, IP, r0 >, < Ledu/nyu/websocket/ChatClient$2;, new >, < Ledu/nyu/websocket/ChatClient$2;, new >]::[< Ledu/nyu/websocket/ChatClient;, IP, r0 >, < Ljava/awt/event/ActionEvent;, IP, r1 >]
 68 new             [< Ledu/nyu/websocket/ChatClient;, IP, r0 >, < Ledu/nyu/websocket/ChatClient$2;, new >, < Ledu/nyu/websocket/ChatClient$2;, new >, < Ledu/nyu/websocket/ChatClient;, IP, r0 >]::[< Ledu/nyu/websocket/ChatClient;, IP, r0 >, < Ljava/awt/event/ActionEvent;, IP, r1 >]
 71 dup             [< Ledu/nyu/websocket/ChatClient;, IP, r0 >, < Ledu/nyu/websocket/ChatClient$2;, new >, < Ledu/nyu/websocket/ChatClient$2;, new >, < Ledu/nyu/websocket/ChatClient;, IP, r0 >, < Ljava/net/URI;, new >]::[< Ledu/nyu/websocket/ChatClient;, IP, r0 >, < Ljava/awt/event/ActionEvent;, IP, r1 >]
 72 aload_0         [< Ledu/nyu/websocket/ChatClient;, IP, r0 >, < Ledu/nyu/websocket/ChatClient$2;, new >, < Ledu/nyu/websocket/ChatClient$2;, new >, < Ledu/nyu/websocket/ChatClient;, IP, r0 >, < Ljava/net/URI;, new >, < Ljava/net/URI;, new >]::[< Ledu/nyu/websocket/ChatClient;, IP, r0 >, < Ljava/awt/event/ActionEvent;, IP, r1 >]
 73 getfield        [< Ledu/nyu/websocket/ChatClient;, IP, r0 >, < Ledu/nyu/websocket/ChatClient$2;, new >, < Ledu/nyu/websocket/ChatClient$2;, new >, < Ledu/nyu/websocket/ChatClient;, IP, r0 >, < Ljava/net/URI;, new >, < Ljava/net/URI;, new >, < Ledu/nyu/websocket/ChatClient;, IP, r0 >]::[< Ledu/nyu/websocket/ChatClient;, IP, r0 >, < Ljava/awt/event/ActionEvent;, IP, r1 >]
 76 invokevirtual   [< Ledu/nyu/websocket/ChatClient;, IP, r0 >, < Ledu/nyu/websocket/ChatClient$2;, new >, < Ledu/nyu/websocket/ChatClient$2;, new >, < Ledu/nyu/websocket/ChatClient;, IP, r0 >, < Ljava/net/URI;, new >, < Ljava/net/URI;, new >, < Ljavax/swing/JTextField;, 0:edu.nyu.websocket.ChatClient.uriField Ljavax/swing/JTextField; >]::[< Ledu/nyu/websocket/ChatClient;, IP, r0 >, < Ljava/awt/event/ActionEvent;, IP, r1 >]
 79 invokespecial   [< Ledu/nyu/websocket/ChatClient;, IP, r0 >, < Ledu/nyu/websocket/ChatClient$2;, new >, < Ledu/nyu/websocket/ChatClient$2;, new >, < Ledu/nyu/websocket/ChatClient;, IP, r0 >, < Ljava/net/URI;, new >, < Ljava/net/URI;, new >, < Ljava/lang/String;, return value from javax.swing.JTextField.getText() >]::[< Ledu/nyu/websocket/ChatClient;, IP, r0 >, < Ljava/awt/event/ActionEvent;, IP, r1 >]
 82 aload_0         [< Ledu/nyu/websocket/ChatClient;, IP, r0 >, < Ledu/nyu/websocket/ChatClient$2;, new >, < Ledu/nyu/websocket/ChatClient$2;, new >, < Ledu/nyu/websocket/ChatClient;, IP, r0 >, < Ljava/net/URI;, new, return value from java.net.URI.<init>(Ljava/lang/String;)V >]::[< Ledu/nyu/websocket/ChatClient;, IP, r0 >, < Ljava/awt/event/ActionEvent;, IP, r1 >]
 83 getfield        [< Ledu/nyu/websocket/ChatClient;, IP, r0 >, < Ledu/nyu/websocket/ChatClient$2;, new >, < Ledu/nyu/websocket/ChatClient$2;, new >, < Ledu/nyu/websocket/ChatClient;, IP, r0 >, < Ljava/net/URI;, new, return value from java.net.URI.<init>(Ljava/lang/String;)V >, < Ledu/nyu/websocket/ChatClient;, IP, r0 >]::[< Ledu/nyu/websocket/ChatClient;, IP, r0 >, < Ljava/awt/event/ActionEvent;, IP, r1 >]
 86 invokevirtual   [< Ledu/nyu/websocket/ChatClient;, IP, r0 >, < Ledu/nyu/websocket/ChatClient$2;, new >, < Ledu/nyu/websocket/ChatClient$2;, new >, < Ledu/nyu/websocket/ChatClient;, IP, r0 >, < Ljava/net/URI;, new, return value from java.net.URI.<init>(Ljava/lang/String;)V >, < Ljavax/swing/JComboBox;, 0:edu.nyu.websocket.ChatClient.draft Ljavax/swing/JComboBox; >]::[< Ledu/nyu/websocket/ChatClient;, IP, r0 >, < Ljava/awt/event/ActionEvent;, IP, r1 >]
 89 checkcast       [< Ledu/nyu/websocket/ChatClient;, IP, r0 >, < Ledu/nyu/websocket/ChatClient$2;, new >, < Ledu/nyu/websocket/ChatClient$2;, new >, < Ledu/nyu/websocket/ChatClient;, IP, r0 >, < Ljava/net/URI;, new, return value from java.net.URI.<init>(Ljava/lang/String;)V >, < Ljava/lang/Object;, return value from javax.swing.JComboBox.getSelectedItem()Ljava/lang/Object; >]::[< Ledu/nyu/websocket/ChatClient;, IP, r0 >, < Ljava/awt/event/ActionEvent;, IP, r1 >]
 92 invokespecial   [< Ledu/nyu/websocket/ChatClient;, IP, r0 >, < Ledu/nyu/websocket/ChatClient$2;, new >, < Ledu/nyu/websocket/ChatClient$2;, new >, < Ledu/nyu/websocket/ChatClient;, IP, r0 >, < Ljava/net/URI;, new, return value from java.net.URI.<init>(Ljava/lang/String;)V >, < Lorg/java_websocket/drafts/Draft;, return value from javax.swing.JComboBox.getSelectedItem()Ljava/lang/Object; >]::[< Ledu/nyu/websocket/ChatClient;, IP, r0 >, < Ljava/awt/event/ActionEvent;, IP, r1 >]
 95 putfield        [< Ledu/nyu/websocket/ChatClient;, IP, r0 >, < Ledu/nyu/websocket/ChatClient$2;, new, return value from edu.nyu.websocket.ChatClient$2.<init>(edu.nyu.websocket.ChatClient, java.net.URI, org.java_websocket.drafts.Draft) >]::[< Ledu/nyu/websocket/ChatClient;, IP, r0 >, < Ljava/awt/event/ActionEvent;, IP, r1 >]
 98 aload_0         []::[< Ledu/nyu/websocket/ChatClient;, IP, r0 >, < Ljava/awt/event/ActionEvent;, IP, r1 >]
 99 getfield        [< Ledu/nyu/websocket/ChatClient;, IP, r0 >]::[< Ledu/nyu/websocket/ChatClient;, IP, r0 >, < Ljava/awt/event/ActionEvent;, IP, r1 >]
102 iconst_1        [< Ljavax/swing/JButton;, 0:edu.nyu.websocket.ChatClient.close Ljavax/swing/JButton; >]::[< Ledu/nyu/websocket/ChatClient;, IP, r0 >, < Ljava/awt/event/ActionEvent;, IP, r1 >]
103 invokevirtual   [< Ljavax/swing/JButton;, 0:edu.nyu.websocket.ChatClient.close Ljavax/swing/JButton; >, < I, 1 >]::[< Ledu/nyu/websocket/ChatClient;, IP, r0 >, < Ljava/awt/event/ActionEvent;, IP, r1 >]
106 aload_0         []::[< Ledu/nyu/websocket/ChatClient;, IP, r0 >, < Ljava/awt/event/ActionEvent;, IP, r1 >]
107 getfield        [< Ledu/nyu/websocket/ChatClient;, IP, r0 >]::[< Ledu/nyu/websocket/ChatClient;, IP, r0 >, < Ljava/awt/event/ActionEvent;, IP, r1 >]
110 iconst_0        [< Ljavax/swing/JButton;, 0:edu.nyu.websocket.ChatClient.connect Ljavax/swing/JButton; >]::[< Ledu/nyu/websocket/ChatClient;, IP, r0 >, < Ljava/awt/event/ActionEvent;, IP, r1 >]
111 invokevirtual   [< Ljavax/swing/JButton;, 0:edu.nyu.websocket.ChatClient.connect Ljavax/swing/JButton; >, < I, 0 >]::[< Ledu/nyu/websocket/ChatClient;, IP, r0 >, < Ljava/awt/event/ActionEvent;, IP, r1 >]
114 aload_0         []::[< Ledu/nyu/websocket/ChatClient;, IP, r0 >, < Ljava/awt/event/ActionEvent;, IP, r1 >]
115 getfield        [< Ledu/nyu/websocket/ChatClient;, IP, r0 >]::[< Ledu/nyu/websocket/ChatClient;, IP, r0 >, < Ljava/awt/event/ActionEvent;, IP, r1 >]
118 iconst_0        [< Ljavax/swing/JTextField;, 0:edu.nyu.websocket.ChatClient.uriField Ljavax/swing/JTextField; >]::[< Ledu/nyu/websocket/ChatClient;, IP, r0 >, < Ljava/awt/event/ActionEvent;, IP, r1 >]
119 invokevirtual   [< Ljavax/swing/JTextField;, 0:edu.nyu.websocket.ChatClient.uriField Ljavax/swing/JTextField; >, < I, 0 >]::[< Ledu/nyu/websocket/ChatClient;, IP, r0 >, < Ljava/awt/event/ActionEvent;, IP, r1 >]
122 aload_0         []::[< Ledu/nyu/websocket/ChatClient;, IP, r0 >, < Ljava/awt/event/ActionEvent;, IP, r1 >]
123 getfield        [< Ledu/nyu/websocket/ChatClient;, IP, r0 >]::[< Ledu/nyu/websocket/ChatClient;, IP, r0 >, < Ljava/awt/event/ActionEvent;, IP, r1 >]
126 iconst_0        [< Ljavax/swing/JComboBox;, 0:edu.nyu.websocket.ChatClient.draft Ljavax/swing/JComboBox; >]::[< Ledu/nyu/websocket/ChatClient;, IP, r0 >, < Ljava/awt/event/ActionEvent;, IP, r1 >]
127 invokevirtual   [< Ljavax/swing/JComboBox;, 0:edu.nyu.websocket.ChatClient.draft Ljavax/swing/JComboBox; >, < I, 0 >]::[< Ledu/nyu/websocket/ChatClient;, IP, r0 >, < Ljava/awt/event/ActionEvent;, IP, r1 >]
130 aload_0         []::[< Ledu/nyu/websocket/ChatClient;, IP, r0 >, < Ljava/awt/event/ActionEvent;, IP, r1 >]
131 getfield        [< Ledu/nyu/websocket/ChatClient;, IP, r0 >]::[< Ledu/nyu/websocket/ChatClient;, IP, r0 >, < Ljava/awt/event/ActionEvent;, IP, r1 >]
134 invokevirtual   [< Ledu/nyu/websocket/ChatClient$2;, 0:edu.nyu.websocket.ChatClient.cc Lorg/java_websocket/client/WebSocketClient; >]::[< Ledu/nyu/websocket/ChatClient;, IP, r0 >, < Ljava/awt/event/ActionEvent;, IP, r1 >]
137 goto            []::[< Ledu/nyu/websocket/ChatClient;, IP, r0 >, < Ljava/awt/event/ActionEvent;, IP, r1 >]
140 astore_2        [< Ljava/net/URISyntaxException; >]::[< Ledu/nyu/websocket/ChatClient;, IP, r0 >, < Ljava/awt/event/ActionEvent;, IP, r1 >]
141 aload_0         []::[< Ledu/nyu/websocket/ChatClient;, IP, r0 >, < Ljava/awt/event/ActionEvent;, IP, r1 >, < Ljava/net/URISyntaxException;, r2 >]
142 getfield        [< Ledu/nyu/websocket/ChatClient;, IP, r0 >]::[< Ledu/nyu/websocket/ChatClient;, IP, r0 >, < Ljava/awt/event/ActionEvent;, IP, r1 >, < Ljava/net/URISyntaxException;, r2 >]
145 aload_0         [< Ljavax/swing/JTextArea;, 0:edu.nyu.websocket.ChatClient.ta Ljavax/swing/JTextArea; >]::[< Ledu/nyu/websocket/ChatClient;, IP, r0 >, < Ljava/awt/event/ActionEvent;, IP, r1 >, < Ljava/net/URISyntaxException;, r2 >]
146 getfield        [< Ljavax/swing/JTextArea;, 0:edu.nyu.websocket.ChatClient.ta Ljavax/swing/JTextArea; >, < Ledu/nyu/websocket/ChatClient;, IP, r0 >]::[< Ledu/nyu/websocket/ChatClient;, IP, r0 >, < Ljava/awt/event/ActionEvent;, IP, r1 >, < Ljava/net/URISyntaxException;, r2 >]
149 invokevirtual   [< Ljavax/swing/JTextArea;, 0:edu.nyu.websocket.ChatClient.ta Ljavax/swing/JTextArea; >, < Ljavax/swing/JTextField;, 0:edu.nyu.websocket.ChatClient.uriField Ljavax/swing/JTextField; >]::[< Ledu/nyu/websocket/ChatClient;, IP, r0 >, < Ljava/awt/event/ActionEvent;, IP, r1 >, < Ljava/net/URISyntaxException;, r2 >]
152 invokedynamic   [< Ljavax/swing/JTextArea;, 0:edu.nyu.websocket.ChatClient.ta Ljavax/swing/JTextArea; >, < Ljava/lang/String;, return value from javax.swing.JTextField.getText() >]::[< Ledu/nyu/websocket/ChatClient;, IP, r0 >, < Ljava/awt/event/ActionEvent;, IP, r1 >, < Ljava/net/URISyntaxException;, r2 >]
157 invokevirtual   [< Ljavax/swing/JTextArea;, 0:edu.nyu.websocket.ChatClient.ta Ljavax/swing/JTextArea; >, < Ljava/lang/String; >]::[< Ledu/nyu/websocket/ChatClient;, IP, r0 >, < Ljava/awt/event/ActionEvent;, IP, r1 >, < Ljava/net/URISyntaxException;, r2 >]
160 goto            []::[< Ledu/nyu/websocket/ChatClient;, IP, r0 >, < Ljava/awt/event/ActionEvent;, IP, r1 >, < Ljava/net/URISyntaxException;, r2 >]
163 aload_1         []::[< Ledu/nyu/websocket/ChatClient;, IP, r0 >, < Ljava/awt/event/ActionEvent;, IP, r1 >]
164 invokevirtual   [< Ljava/awt/event/ActionEvent;, IP, r1 >]::[< Ledu/nyu/websocket/ChatClient;, IP, r0 >, < Ljava/awt/event/ActionEvent;, IP, r1 >]
167 aload_0         [< Ljava/lang/Object;, return value from java.awt.AWTEvent.getSource() >]::[< Ledu/nyu/websocket/ChatClient;, IP, r0 >, < Ljava/awt/event/ActionEvent;, IP, r1 >]
168 getfield        [< Ljava/lang/Object;, return value from java.awt.AWTEvent.getSource() >, < Ledu/nyu/websocket/ChatClient;, IP, r0 >]::[< Ledu/nyu/websocket/ChatClient;, IP, r0 >, < Ljava/awt/event/ActionEvent;, IP, r1 >]
171 if_acmpne       [< Ljava/lang/Object;, return value from java.awt.AWTEvent.getSource() >, < Ljavax/swing/JButton;, 0:edu.nyu.websocket.ChatClient.close Ljavax/swing/JButton; >]::[< Ledu/nyu/websocket/ChatClient;, IP, r0 >, < Ljava/awt/event/ActionEvent;, IP, r1 >]
174 aload_0         []::[< Ledu/nyu/websocket/ChatClient;, IP, r0 >, < Ljava/awt/event/ActionEvent;, IP, r1 >]
175 getfield        [< Ledu/nyu/websocket/ChatClient;, IP, r0 >]::[< Ledu/nyu/websocket/ChatClient;, IP, r0 >, < Ljava/awt/event/ActionEvent;, IP, r1 >]
178 invokevirtual   [< Ledu/nyu/websocket/ChatClient$2;, 0:edu.nyu.websocket.ChatClient.cc Lorg/java_websocket/client/WebSocketClient; >]::[< Ledu/nyu/websocket/ChatClient;, IP, r0 >, < Ljava/awt/event/ActionEvent;, IP, r1 >]
181 return          []::[< Ledu/nyu/websocket/ChatClient;, IP, r0 >, < Ljava/awt/event/ActionEvent;, IP, r1 >]

edu.nyu.websocket.ChatClient.main : ([Ljava.lang.String;)V
  0 aload_0         []::[< [Ljava/lang/String;, IP, r0 >]
  1 arraylength     [< [Ljava/lang/String;, IP, r0 >]::[< [Ljava/lang/String;, IP, r0 >]
  2 ifeq            [< I, non_negative >]::[< [Ljava/lang/String;, IP, r0 >]
  5 aload_0         []::[< [Ljava/lang/String;, IP, r0 >]
  6 iconst_0        [< [Ljava/lang/String;, IP, r0 >]::[< [Ljava/lang/String;, IP, r0 >]
  7 aaload          [< [Ljava/lang/String;, IP, r0 >, < I, 0 >]::[< [Ljava/lang/String;, IP, r0 >]
  8 astore_1        [< Ljava/lang/String; >]::[< [Ljava/lang/String;, IP, r0 >]
  9 getstatic       []::[< [Ljava/lang/String;, IP, r0 >, < Ljava/lang/String;, r1 >]
 12 aload_1         [< Ljava/io/PrintStream;, static java.lang.System.out Ljava/io/PrintStream; >]::[< [Ljava/lang/String;, IP, r0 >, < Ljava/lang/String;, r1 >]
 13 invokedynamic   [< Ljava/io/PrintStream;, static java.lang.System.out Ljava/io/PrintStream; >, < Ljava/lang/String;, r1 >]::[< [Ljava/lang/String;, IP, r0 >, < Ljava/lang/String;, r1 >]
 18 invokevirtual   [< Ljava/io/PrintStream;, static java.lang.System.out Ljava/io/PrintStream; >, < Ljava/lang/String; >]::[< [Ljava/lang/String;, IP, r0 >, < Ljava/lang/String;, r1 >]
 21 goto            []::[< [Ljava/lang/String;, IP, r0 >, < Ljava/lang/String;, r1 >]
 24 ldc             []::[< [Ljava/lang/String;, IP, r0 >]
 26 astore_1        [< Ljava/lang/String;, "ws://localhost:8887" >]::[< [Ljava/lang/String;, IP, r0 >]
 27 getstatic       []::[< [Ljava/lang/String;, IP, r0 >, < Ljava/lang/String;, "ws://localhost:8887", r1 >]
 30 aload_1         [< Ljava/io/PrintStream;, static java.lang.System.out Ljava/io/PrintStream; >]::[< [Ljava/lang/String;, IP, r0 >, < Ljava/lang/String;, "ws://localhost:8887", r1 >]
 31 invokedynamic   [< Ljava/io/PrintStream;, static java.lang.System.out Ljava/io/PrintStream; >, < Ljava/lang/String;, "ws://localhost:8887", r1 >]::[< [Ljava/lang/String;, IP, r0 >, < Ljava/lang/String;, "ws://localhost:8887", r1 >]
 36 invokevirtual   [< Ljava/io/PrintStream;, static java.lang.System.out Ljava/io/PrintStream; >, < Ljava/lang/String;, "Default server url not specified: defaulting to 'ws://localhost:8887'" >]::[< [Ljava/lang/String;, IP, r0 >, < Ljava/lang/String;, "ws://localhost:8887", r1 >]
 39 new             []::[< [Ljava/lang/String;, IP, r0 >, < Ljava/lang/String;, r1 >]
 42 dup             [< Ledu/nyu/websocket/ChatClient;, new >]::[< [Ljava/lang/String;, IP, r0 >, < Ljava/lang/String;, r1 >]
 43 aload_1         [< Ledu/nyu/websocket/ChatClient;, new >, < Ledu/nyu/websocket/ChatClient;, new >]::[< [Ljava/lang/String;, IP, r0 >, < Ljava/lang/String;, r1 >]
 44 invokespecial   [< Ledu/nyu/websocket/ChatClient;, new >, < Ledu/nyu/websocket/ChatClient;, new >, < Ljava/lang/String;, r1 >]::[< [Ljava/lang/String;, IP, r0 >, < Ljava/lang/String;, r1 >]
 47 pop             [< Ledu/nyu/websocket/ChatClient;, new, return value from edu.nyu.websocket.ChatClient.<init>(Ljava/lang/String;)V >]::[< [Ljava/lang/String;, IP, r0 >, < Ljava/lang/String;, r1 >]
 48 return          []::[< [Ljava/lang/String;, IP, r0 >, < Ljava/lang/String;, r1 >]
