edu.nyu.websocket.ChatServer.<init> : (I)V
  0 aload_0         []::[< Ledu/nyu/websocket/ChatServer;, IP, r0 >, < I, IP, r1 >]
  1 new             [< Ledu/nyu/websocket/ChatServer;, IP, r0 >]::[< Ledu/nyu/websocket/ChatServer;, IP, r0 >, < I, IP, r1 >]
  4 dup             [< Ledu/nyu/websocket/ChatServer;, IP, r0 >, < Ljava/net/InetSocketAddress;, new >]::[< Ledu/nyu/websocket/ChatServer;, IP, r0 >, < I, IP, r1 >]
  5 iload_1         [< Ledu/nyu/websocket/ChatServer;, IP, r0 >, < Ljava/net/InetSocketAddress;, new >, < Ljava/net/InetSocketAddress;, new >]::[< Ledu/nyu/websocket/ChatServer;, IP, r0 >, < I, IP, r1 >]
  6 invokespecial   [< Ledu/nyu/websocket/ChatServer;, IP, r0 >, < Ljava/net/InetSocketAddress;, new >, < Ljava/net/InetSocketAddress;, new >, < I, IP, r1 >]::[< Ledu/nyu/websocket/ChatServer;, IP, r0 >, < I, IP, r1 >]
  9 invokespecial   [< Ledu/nyu/websocket/ChatServer;, IP, r0 >, < Ljava/net/InetSocketAddress;, new, return value from java.net.InetSocketAddress.<init>(I)V >]::[< Ledu/nyu/websocket/ChatServer;, IP, r0 >, < I, IP, r1 >]
 12 return          []::[< Ledu/nyu/websocket/ChatServer;, IP, r0 >, < I, IP, r1 >]

edu.nyu.websocket.ChatServer.<init> : (Ljava.net.InetSocketAddress;)V
  0 aload_0         []::[< Ledu/nyu/websocket/ChatServer;, IP, r0 >, < Ljava/net/InetSocketAddress;, IP, r1 >]
  1 aload_1         [< Ledu/nyu/websocket/ChatServer;, IP, r0 >]::[< Ledu/nyu/websocket/ChatServer;, IP, r0 >, < Ljava/net/InetSocketAddress;, IP, r1 >]
  2 invokespecial   [< Ledu/nyu/websocket/ChatServer;, IP, r0 >, < Ljava/net/InetSocketAddress;, IP, r1 >]::[< Ledu/nyu/websocket/ChatServer;, IP, r0 >, < Ljava/net/InetSocketAddress;, IP, r1 >]
  5 return          []::[< Ledu/nyu/websocket/ChatServer;, IP, r0 >, < Ljava/net/InetSocketAddress;, IP, r1 >]

edu.nyu.websocket.ChatServer.<init> : (ILorg.java_websocket.drafts.Draft_6455;)V
  0 aload_0         []::[< Ledu/nyu/websocket/ChatServer;, IP, r0 >, < I, IP, r1 >, < Lorg/java_websocket/drafts/Draft_6455;, IP, r2 >]
  1 new             [< Ledu/nyu/websocket/ChatServer;, IP, r0 >]::[< Ledu/nyu/websocket/ChatServer;, IP, r0 >, < I, IP, r1 >, < Lorg/java_websocket/drafts/Draft_6455;, IP, r2 >]
  4 dup             [< Ledu/nyu/websocket/ChatServer;, IP, r0 >, < Ljava/net/InetSocketAddress;, new >]::[< Ledu/nyu/websocket/ChatServer;, IP, r0 >, < I, IP, r1 >, < Lorg/java_websocket/drafts/Draft_6455;, IP, r2 >]
  5 iload_1         [< Ledu/nyu/websocket/ChatServer;, IP, r0 >, < Ljava/net/InetSocketAddress;, new >, < Ljava/net/InetSocketAddress;, new >]::[< Ledu/nyu/websocket/ChatServer;, IP, r0 >, < I, IP, r1 >, < Lorg/java_websocket/drafts/Draft_6455;, IP, r2 >]
  6 invokespecial   [< Ledu/nyu/websocket/ChatServer;, IP, r0 >, < Ljava/net/InetSocketAddress;, new >, < Ljava/net/InetSocketAddress;, new >, < I, IP, r1 >]::[< Ledu/nyu/websocket/ChatServer;, IP, r0 >, < I, IP, r1 >, < Lorg/java_websocket/drafts/Draft_6455;, IP, r2 >]
  9 aload_2         [< Ledu/nyu/websocket/ChatServer;, IP, r0 >, < Ljava/net/InetSocketAddress;, new, return value from java.net.InetSocketAddress.<init>(I)V >]::[< Ledu/nyu/websocket/ChatServer;, IP, r0 >, < I, IP, r1 >, < Lorg/java_websocket/drafts/Draft_6455;, IP, r2 >]
 10 invokestatic    [< Ledu/nyu/websocket/ChatServer;, IP, r0 >, < Ljava/net/InetSocketAddress;, new, return value from java.net.InetSocketAddress.<init>(I)V >, < Lorg/java_websocket/drafts/Draft_6455;, IP, r2 >]::[< Ledu/nyu/websocket/ChatServer;, IP, r0 >, < I, IP, r1 >, < Lorg/java_websocket/drafts/Draft_6455;, IP, r2 >]
 13 invokespecial   [< Ledu/nyu/websocket/ChatServer;, IP, r0 >, < Ljava/net/InetSocketAddress;, new, return value from java.net.InetSocketAddress.<init>(I)V >, < Ljava/util/Collections$SingletonList; >]::[< Ledu/nyu/websocket/ChatServer;, IP, r0 >, < I, IP, r1 >, < Lorg/java_websocket/drafts/Draft_6455;, IP, r2 >]
 16 return          []::[< Ledu/nyu/websocket/ChatServer;, IP, r0 >, < I, IP, r1 >, < Lorg/java_websocket/drafts/Draft_6455;, IP, r2 >]

edu.nyu.websocket.ChatServer.onOpen : (Lorg.java_websocket.WebSocket;Lorg.java_websocket.handshake.ClientHandshake;)V
  0 aload_1         []::[< Ledu/nyu/websocket/ChatServer;, IP, r0 >, < Lorg/java_websocket/WebSocket;, IP, r1 >, < Lorg/java_websocket/handshake/ClientHandshake;, IP, r2 >]
  1 ldc             [< Lorg/java_websocket/WebSocket;, IP, r1 >]::[< Ledu/nyu/websocket/ChatServer;, IP, r0 >, < Lorg/java_websocket/WebSocket;, IP, r1 >, < Lorg/java_websocket/handshake/ClientHandshake;, IP, r2 >]
  3 invokeinterface [< Lorg/java_websocket/WebSocket;, IP, r1 >, < Ljava/lang/String;, "Welcome to the server!" >]::[< Ledu/nyu/websocket/ChatServer;, IP, r0 >, < Lorg/java_websocket/WebSocket;, IP, r1 >, < Lorg/java_websocket/handshake/ClientHandshake;, IP, r2 >]
  8 aload_0         []::[< Ledu/nyu/websocket/ChatServer;, IP, r0 >, < Lorg/java_websocket/WebSocket;, IP, r1 >, < Lorg/java_websocket/handshake/ClientHandshake;, IP, r2 >]
  9 aload_2         [< Ledu/nyu/websocket/ChatServer;, IP, r0 >]::[< Ledu/nyu/websocket/ChatServer;, IP, r0 >, < Lorg/java_websocket/WebSocket;, IP, r1 >, < Lorg/java_websocket/handshake/ClientHandshake;, IP, r2 >]
 10 invokeinterface [< Ledu/nyu/websocket/ChatServer;, IP, r0 >, < Lorg/java_websocket/handshake/ClientHandshake;, IP, r2 >]::[< Ledu/nyu/websocket/ChatServer;, IP, r0 >, < Lorg/java_websocket/WebSocket;, IP, r1 >, < Lorg/java_websocket/handshake/ClientHandshake;, IP, r2 >]
 15 invokedynamic   [< Ledu/nyu/websocket/ChatServer;, IP, r0 >, < Ljava/lang/String;, return value from org.java_websocket.handshake.ClientHandshake.getResourceDescriptor() >]::[< Ledu/nyu/websocket/ChatServer;, IP, r0 >, < Lorg/java_websocket/WebSocket;, IP, r1 >, < Lorg/java_websocket/handshake/ClientHandshake;, IP, r2 >]
 20 invokevirtual   [< Ledu/nyu/websocket/ChatServer;, IP, r0 >, < Ljava/lang/String; >]::[< Ledu/nyu/websocket/ChatServer;, IP, r0 >, < Lorg/java_websocket/WebSocket;, IP, r1 >, < Lorg/java_websocket/handshake/ClientHandshake;, IP, r2 >]
 23 getstatic       []::[< Ledu/nyu/websocket/ChatServer;, IP, r0 >, < Lorg/java_websocket/WebSocket;, IP, r1 >, < Lorg/java_websocket/handshake/ClientHandshake;, IP, r2 >]
 26 aload_1         [< Ljava/io/PrintStream;, static java.lang.System.out Ljava/io/PrintStream; >]::[< Ledu/nyu/websocket/ChatServer;, IP, r0 >, < Lorg/java_websocket/WebSocket;, IP, r1 >, < Lorg/java_websocket/handshake/ClientHandshake;, IP, r2 >]
 27 invokeinterface [< Ljava/io/PrintStream;, static java.lang.System.out Ljava/io/PrintStream; >, < Lorg/java_websocket/WebSocket;, IP, r1 >]::[< Ledu/nyu/websocket/ChatServer;, IP, r0 >, < Lorg/java_websocket/WebSocket;, IP, r1 >, < Lorg/java_websocket/handshake/ClientHandshake;, IP, r2 >]
 32 invokevirtual   [< Ljava/io/PrintStream;, static java.lang.System.out Ljava/io/PrintStream; >, < Ljava/net/InetSocketAddress;, return value from org.java_websocket.WebSocket.getRemoteSocketAddress() >]::[< Ledu/nyu/websocket/ChatServer;, IP, r0 >, < Lorg/java_websocket/WebSocket;, IP, r1 >, < Lorg/java_websocket/handshake/ClientHandshake;, IP, r2 >]
 35 invokevirtual   [< Ljava/io/PrintStream;, static java.lang.System.out Ljava/io/PrintStream; >, < Ljava/net/InetAddress;, return value from java.net.InetSocketAddress.getAddress()Ljava/net/InetAddress; >]::[< Ledu/nyu/websocket/ChatServer;, IP, r0 >, < Lorg/java_websocket/WebSocket;, IP, r1 >, < Lorg/java_websocket/handshake/ClientHandshake;, IP, r2 >]
 38 invokedynamic   [< Ljava/io/PrintStream;, static java.lang.System.out Ljava/io/PrintStream; >, < Ljava/lang/String;, return value from java.net.InetAddress.getHostAddress()Ljava/lang/String; >]::[< Ledu/nyu/websocket/ChatServer;, IP, r0 >, < Lorg/java_websocket/WebSocket;, IP, r1 >, < Lorg/java_websocket/handshake/ClientHandshake;, IP, r2 >]
 43 invokevirtual   [< Ljava/io/PrintStream;, static java.lang.System.out Ljava/io/PrintStream; >, < Ljava/lang/String; >]::[< Ledu/nyu/websocket/ChatServer;, IP, r0 >, < Lorg/java_websocket/WebSocket;, IP, r1 >, < Lorg/java_websocket/handshake/ClientHandshake;, IP, r2 >]
 46 return          []::[< Ledu/nyu/websocket/ChatServer;, IP, r0 >, < Lorg/java_websocket/WebSocket;, IP, r1 >, < Lorg/java_websocket/handshake/ClientHandshake;, IP, r2 >]

edu.nyu.websocket.ChatServer.onClose : (Lorg.java_websocket.WebSocket;ILjava.lang.String;Z)V
  0 aload_0         []::[< Ledu/nyu/websocket/ChatServer;, IP, r0 >, < Lorg/java_websocket/WebSocket;, IP, r1 >, < I, IP, r2 >, < Ljava/lang/String;, IP, r3 >, < Z, IP, r4 >]
  1 aload_1         [< Ledu/nyu/websocket/ChatServer;, IP, r0 >]::[< Ledu/nyu/websocket/ChatServer;, IP, r0 >, < Lorg/java_websocket/WebSocket;, IP, r1 >, < I, IP, r2 >, < Ljava/lang/String;, IP, r3 >, < Z, IP, r4 >]
  2 invokestatic    [< Ledu/nyu/websocket/ChatServer;, IP, r0 >, < Lorg/java_websocket/WebSocket;, IP, r1 >]::[< Ledu/nyu/websocket/ChatServer;, IP, r0 >, < Lorg/java_websocket/WebSocket;, IP, r1 >, < I, IP, r2 >, < Ljava/lang/String;, IP, r3 >, < Z, IP, r4 >]
  5 invokedynamic   [< Ledu/nyu/websocket/ChatServer;, IP, r0 >, < Ljava/lang/String;, return value from static java.lang.String.valueOf(Ljava/lang/Object;)Ljava/lang/String; >]::[< Ledu/nyu/websocket/ChatServer;, IP, r0 >, < Lorg/java_websocket/WebSocket;, IP, r1 >, < I, IP, r2 >, < Ljava/lang/String;, IP, r3 >, < Z, IP, r4 >]
 10 invokevirtual   [< Ledu/nyu/websocket/ChatServer;, IP, r0 >, < Ljava/lang/String; >]::[< Ledu/nyu/websocket/ChatServer;, IP, r0 >, < Lorg/java_websocket/WebSocket;, IP, r1 >, < I, IP, r2 >, < Ljava/lang/String;, IP, r3 >, < Z, IP, r4 >]
 13 getstatic       []::[< Ledu/nyu/websocket/ChatServer;, IP, r0 >, < Lorg/java_websocket/WebSocket;, IP, r1 >, < I, IP, r2 >, < Ljava/lang/String;, IP, r3 >, < Z, IP, r4 >]
 16 aload_1         [< Ljava/io/PrintStream;, static java.lang.System.out Ljava/io/PrintStream; >]::[< Ledu/nyu/websocket/ChatServer;, IP, r0 >, < Lorg/java_websocket/WebSocket;, IP, r1 >, < I, IP, r2 >, < Ljava/lang/String;, IP, r3 >, < Z, IP, r4 >]
 17 invokestatic    [< Ljava/io/PrintStream;, static java.lang.System.out Ljava/io/PrintStream; >, < Lorg/java_websocket/WebSocket;, IP, r1 >]::[< Ledu/nyu/websocket/ChatServer;, IP, r0 >, < Lorg/java_websocket/WebSocket;, IP, r1 >, < I, IP, r2 >, < Ljava/lang/String;, IP, r3 >, < Z, IP, r4 >]
 20 invokedynamic   [< Ljava/io/PrintStream;, static java.lang.System.out Ljava/io/PrintStream; >, < Ljava/lang/String;, return value from static java.lang.String.valueOf(Ljava/lang/Object;)Ljava/lang/String; >]::[< Ledu/nyu/websocket/ChatServer;, IP, r0 >, < Lorg/java_websocket/WebSocket;, IP, r1 >, < I, IP, r2 >, < Ljava/lang/String;, IP, r3 >, < Z, IP, r4 >]
 25 invokevirtual   [< Ljava/io/PrintStream;, static java.lang.System.out Ljava/io/PrintStream; >, < Ljava/lang/String; >]::[< Ledu/nyu/websocket/ChatServer;, IP, r0 >, < Lorg/java_websocket/WebSocket;, IP, r1 >, < I, IP, r2 >, < Ljava/lang/String;, IP, r3 >, < Z, IP, r4 >]
 28 return          []::[< Ledu/nyu/websocket/ChatServer;, IP, r0 >, < Lorg/java_websocket/WebSocket;, IP, r1 >, < I, IP, r2 >, < Ljava/lang/String;, IP, r3 >, < Z, IP, r4 >]

edu.nyu.websocket.ChatServer.onMessage : (Lorg.java_websocket.WebSocket;Ljava.lang.String;)V
  0 aload_0         []::[< Ledu/nyu/websocket/ChatServer;, IP, r0 >, < Lorg/java_websocket/WebSocket;, IP, r1 >, < Ljava/lang/String;, IP, r2 >]
  1 aload_2         [< Ledu/nyu/websocket/ChatServer;, IP, r0 >]::[< Ledu/nyu/websocket/ChatServer;, IP, r0 >, < Lorg/java_websocket/WebSocket;, IP, r1 >, < Ljava/lang/String;, IP, r2 >]
  2 invokevirtual   [< Ledu/nyu/websocket/ChatServer;, IP, r0 >, < Ljava/lang/String;, IP, r2 >]::[< Ledu/nyu/websocket/ChatServer;, IP, r0 >, < Lorg/java_websocket/WebSocket;, IP, r1 >, < Ljava/lang/String;, IP, r2 >]
  5 getstatic       []::[< Ledu/nyu/websocket/ChatServer;, IP, r0 >, < Lorg/java_websocket/WebSocket;, IP, r1 >, < Ljava/lang/String;, IP, r2 >]
  8 aload_1         [< Ljava/io/PrintStream;, static java.lang.System.out Ljava/io/PrintStream; >]::[< Ledu/nyu/websocket/ChatServer;, IP, r0 >, < Lorg/java_websocket/WebSocket;, IP, r1 >, < Ljava/lang/String;, IP, r2 >]
  9 invokestatic    [< Ljava/io/PrintStream;, static java.lang.System.out Ljava/io/PrintStream; >, < Lorg/java_websocket/WebSocket;, IP, r1 >]::[< Ledu/nyu/websocket/ChatServer;, IP, r0 >, < Lorg/java_websocket/WebSocket;, IP, r1 >, < Ljava/lang/String;, IP, r2 >]
 12 aload_2         [< Ljava/io/PrintStream;, static java.lang.System.out Ljava/io/PrintStream; >, < Ljava/lang/String;, return value from static java.lang.String.valueOf(Ljava/lang/Object;)Ljava/lang/String; >]::[< Ledu/nyu/websocket/ChatServer;, IP, r0 >, < Lorg/java_websocket/WebSocket;, IP, r1 >, < Ljava/lang/String;, IP, r2 >]
 13 invokedynamic   [< Ljava/io/PrintStream;, static java.lang.System.out Ljava/io/PrintStream; >, < Ljava/lang/String;, return value from static java.lang.String.valueOf(Ljava/lang/Object;)Ljava/lang/String; >, < Ljava/lang/String;, IP, r2 >]::[< Ledu/nyu/websocket/ChatServer;, IP, r0 >, < Lorg/java_websocket/WebSocket;, IP, r1 >, < Ljava/lang/String;, IP, r2 >]
 18 invokevirtual   [< Ljava/io/PrintStream;, static java.lang.System.out Ljava/io/PrintStream; >, < Ljava/lang/String; >]::[< Ledu/nyu/websocket/ChatServer;, IP, r0 >, < Lorg/java_websocket/WebSocket;, IP, r1 >, < Ljava/lang/String;, IP, r2 >]
 21 return          []::[< Ledu/nyu/websocket/ChatServer;, IP, r0 >, < Lorg/java_websocket/WebSocket;, IP, r1 >, < Ljava/lang/String;, IP, r2 >]

edu.nyu.websocket.ChatServer.onMessage : (Lorg.java_websocket.WebSocket;Ljava.nio.ByteBuffer;)V
  0 aload_0         []::[< Ledu/nyu/websocket/ChatServer;, IP, r0 >, < Lorg/java_websocket/WebSocket;, IP, r1 >, < Ljava/nio/ByteBuffer;, IP, r2 >]
  1 aload_2         [< Ledu/nyu/websocket/ChatServer;, IP, r0 >]::[< Ledu/nyu/websocket/ChatServer;, IP, r0 >, < Lorg/java_websocket/WebSocket;, IP, r1 >, < Ljava/nio/ByteBuffer;, IP, r2 >]
  2 invokevirtual   [< Ledu/nyu/websocket/ChatServer;, IP, r0 >, < Ljava/nio/ByteBuffer;, IP, r2 >]::[< Ledu/nyu/websocket/ChatServer;, IP, r0 >, < Lorg/java_websocket/WebSocket;, IP, r1 >, < Ljava/nio/ByteBuffer;, IP, r2 >]
  5 invokevirtual   [< Ledu/nyu/websocket/ChatServer;, IP, r0 >, < [B, return value from java.nio.ByteBuffer.array()[B >]::[< Ledu/nyu/websocket/ChatServer;, IP, r0 >, < Lorg/java_websocket/WebSocket;, IP, r1 >, < Ljava/nio/ByteBuffer;, IP, r2 >]
  8 getstatic       []::[< Ledu/nyu/websocket/ChatServer;, IP, r0 >, < Lorg/java_websocket/WebSocket;, IP, r1 >, < Ljava/nio/ByteBuffer;, IP, r2 >]
 11 aload_1         [< Ljava/io/PrintStream;, static java.lang.System.out Ljava/io/PrintStream; >]::[< Ledu/nyu/websocket/ChatServer;, IP, r0 >, < Lorg/java_websocket/WebSocket;, IP, r1 >, < Ljava/nio/ByteBuffer;, IP, r2 >]
 12 invokestatic    [< Ljava/io/PrintStream;, static java.lang.System.out Ljava/io/PrintStream; >, < Lorg/java_websocket/WebSocket;, IP, r1 >]::[< Ledu/nyu/websocket/ChatServer;, IP, r0 >, < Lorg/java_websocket/WebSocket;, IP, r1 >, < Ljava/nio/ByteBuffer;, IP, r2 >]
 15 aload_2         [< Ljava/io/PrintStream;, static java.lang.System.out Ljava/io/PrintStream; >, < Ljava/lang/String;, return value from static java.lang.String.valueOf(Ljava/lang/Object;)Ljava/lang/String; >]::[< Ledu/nyu/websocket/ChatServer;, IP, r0 >, < Lorg/java_websocket/WebSocket;, IP, r1 >, < Ljava/nio/ByteBuffer;, IP, r2 >]
 16 invokestatic    [< Ljava/io/PrintStream;, static java.lang.System.out Ljava/io/PrintStream; >, < Ljava/lang/String;, return value from static java.lang.String.valueOf(Ljava/lang/Object;)Ljava/lang/String; >, < Ljava/nio/ByteBuffer;, IP, r2 >]::[< Ledu/nyu/websocket/ChatServer;, IP, r0 >, < Lorg/java_websocket/WebSocket;, IP, r1 >, < Ljava/nio/ByteBuffer;, IP, r2 >]
 19 invokedynamic   [< Ljava/io/PrintStream;, static java.lang.System.out Ljava/io/PrintStream; >, < Ljava/lang/String;, return value from static java.lang.String.valueOf(Ljava/lang/Object;)Ljava/lang/String; >, < Ljava/lang/String;, return value from static java.lang.String.valueOf(Ljava/lang/Object;)Ljava/lang/String; >]::[< Ledu/nyu/websocket/ChatServer;, IP, r0 >, < Lorg/java_websocket/WebSocket;, IP, r1 >, < Ljava/nio/ByteBuffer;, IP, r2 >]
 24 invokevirtual   [< Ljava/io/PrintStream;, static java.lang.System.out Ljava/io/PrintStream; >, < Ljava/lang/String; >]::[< Ledu/nyu/websocket/ChatServer;, IP, r0 >, < Lorg/java_websocket/WebSocket;, IP, r1 >, < Ljava/nio/ByteBuffer;, IP, r2 >]
 27 return          []::[< Ledu/nyu/websocket/ChatServer;, IP, r0 >, < Lorg/java_websocket/WebSocket;, IP, r1 >, < Ljava/nio/ByteBuffer;, IP, r2 >]

edu.nyu.websocket.ChatServer.main : ([Ljava.lang.String;)V
  0 sipush          []::[< [Ljava/lang/String;, IP, r0 >]
  3 istore_1        [< I, 8887 >]::[< [Ljava/lang/String;, IP, r0 >]
  4 aload_0         []::[< [Ljava/lang/String;, IP, r0 >, < I, 8887, r1 >]
  5 iconst_0        [< [Ljava/lang/String;, IP, r0 >]::[< [Ljava/lang/String;, IP, r0 >, < I, 8887, r1 >]
  6 aaload          [< [Ljava/lang/String;, IP, r0 >, < I, 0 >]::[< [Ljava/lang/String;, IP, r0 >, < I, 8887, r1 >]
  7 invokestatic    [< Ljava/lang/String; >]::[< [Ljava/lang/String;, IP, r0 >, < I, 8887, r1 >]
 10 istore_1        [< I, return value from static java.lang.Integer.parseInt(Ljava/lang/String;)I >]::[< [Ljava/lang/String;, IP, r0 >, < I, 8887, r1 >]
 11 goto            []::[< [Ljava/lang/String;, IP, r0 >, < I, return value from static java.lang.Integer.parseInt(Ljava/lang/String;)I, r1 >]
 14 astore_2        [< Ljava/lang/Exception; >]::[< [Ljava/lang/String;, IP, r0 >, < I, return value from static java.lang.Integer.parseInt(Ljava/lang/String;)I, r1 >]
 15 new             []::[< [Ljava/lang/String;, IP, r0 >, < I, return value from static java.lang.Integer.parseInt(Ljava/lang/String;)I, r1 >, < Ljava/lang/Exception;, r2 >]
 18 dup             [< Ledu/nyu/websocket/ChatServer;, new >]::[< [Ljava/lang/String;, IP, r0 >, < I, return value from static java.lang.Integer.parseInt(Ljava/lang/String;)I, r1 >, < Ljava/lang/Exception;, r2 >]
 19 iload_1         [< Ledu/nyu/websocket/ChatServer;, new >, < Ledu/nyu/websocket/ChatServer;, new >]::[< [Ljava/lang/String;, IP, r0 >, < I, return value from static java.lang.Integer.parseInt(Ljava/lang/String;)I, r1 >, < Ljava/lang/Exception;, r2 >]
 20 invokespecial   [< Ledu/nyu/websocket/ChatServer;, new >, < Ledu/nyu/websocket/ChatServer;, new >, < I, return value from static java.lang.Integer.parseInt(Ljava/lang/String;)I, r1 >]::[< [Ljava/lang/String;, IP, r0 >, < I, return value from static java.lang.Integer.parseInt(Ljava/lang/String;)I, r1 >, < Ljava/lang/Exception;, r2 >]
 23 astore_2        [< Ledu/nyu/websocket/ChatServer;, new, return value from edu.nyu.websocket.ChatServer.<init>(I)V >]::[< [Ljava/lang/String;, IP, r0 >, < I, return value from static java.lang.Integer.parseInt(Ljava/lang/String;)I, r1 >, < Ljava/lang/Exception;, r2 >]
 24 aload_2         []::[< [Ljava/lang/String;, IP, r0 >, < I, return value from static java.lang.Integer.parseInt(Ljava/lang/String;)I, r1 >, < Ledu/nyu/websocket/ChatServer;, new, return value from edu.nyu.websocket.ChatServer.<init>(I)V, r2 >]
 25 invokevirtual   [< Ledu/nyu/websocket/ChatServer;, new, return value from edu.nyu.websocket.ChatServer.<init>(I)V, r2 >]::[< [Ljava/lang/String;, IP, r0 >, < I, return value from static java.lang.Integer.parseInt(Ljava/lang/String;)I, r1 >, < Ledu/nyu/websocket/ChatServer;, new, return value from edu.nyu.websocket.ChatServer.<init>(I)V, r2 >]
 28 getstatic       []::[< [Ljava/lang/String;, IP, r0 >, < I, return value from static java.lang.Integer.parseInt(Ljava/lang/String;)I, r1 >, < Ledu/nyu/websocket/ChatServer;, new, return value from edu.nyu.websocket.ChatServer.<init>(I)V, r2 >]
 31 aload_2         [< Ljava/io/PrintStream;, static java.lang.System.out Ljava/io/PrintStream; >]::[< [Ljava/lang/String;, IP, r0 >, < I, return value from static java.lang.Integer.parseInt(Ljava/lang/String;)I, r1 >, < Ledu/nyu/websocket/ChatServer;, new, return value from edu.nyu.websocket.ChatServer.<init>(I)V, r2 >]
 32 invokevirtual   [< Ljava/io/PrintStream;, static java.lang.System.out Ljava/io/PrintStream; >, < Ledu/nyu/websocket/ChatServer;, new, return value from edu.nyu.websocket.ChatServer.<init>(I)V, r2 >]::[< [Ljava/lang/String;, IP, r0 >, < I, return value from static java.lang.Integer.parseInt(Ljava/lang/String;)I, r1 >, < Ledu/nyu/websocket/ChatServer;, new, return value from edu.nyu.websocket.ChatServer.<init>(I)V, r2 >]
 35 invokedynamic   [< Ljava/io/PrintStream;, static java.lang.System.out Ljava/io/PrintStream; >, < I, return value from edu.nyu.websocket.ChatServer.getPort() >]::[< [Ljava/lang/String;, IP, r0 >, < I, return value from static java.lang.Integer.parseInt(Ljava/lang/String;)I, r1 >, < Ledu/nyu/websocket/ChatServer;, new, return value from edu.nyu.websocket.ChatServer.<init>(I)V, r2 >]
 40 invokevirtual   [< Ljava/io/PrintStream;, static java.lang.System.out Ljava/io/PrintStream; >, < Ljava/lang/String; >]::[< [Ljava/lang/String;, IP, r0 >, < I, return value from static java.lang.Integer.parseInt(Ljava/lang/String;)I, r1 >, < Ledu/nyu/websocket/ChatServer;, new, return value from edu.nyu.websocket.ChatServer.<init>(I)V, r2 >]
 43 new             []::[< [Ljava/lang/String;, IP, r0 >, < I, return value from static java.lang.Integer.parseInt(Ljava/lang/String;)I, r1 >, < Ledu/nyu/websocket/ChatServer;, new, return value from edu.nyu.websocket.ChatServer.<init>(I)V, r2 >]
 46 dup             [< Ljava/io/BufferedReader;, new >]::[< [Ljava/lang/String;, IP, r0 >, < I, return value from static java.lang.Integer.parseInt(Ljava/lang/String;)I, r1 >, < Ledu/nyu/websocket/ChatServer;, new, return value from edu.nyu.websocket.ChatServer.<init>(I)V, r2 >]
 47 new             [< Ljava/io/BufferedReader;, new >, < Ljava/io/BufferedReader;, new >]::[< [Ljava/lang/String;, IP, r0 >, < I, return value from static java.lang.Integer.parseInt(Ljava/lang/String;)I, r1 >, < Ledu/nyu/websocket/ChatServer;, new, return value from edu.nyu.websocket.ChatServer.<init>(I)V, r2 >]
 50 dup             [< Ljava/io/BufferedReader;, new >, < Ljava/io/BufferedReader;, new >, < Ljava/io/InputStreamReader;, new >]::[< [Ljava/lang/String;, IP, r0 >, < I, return value from static java.lang.Integer.parseInt(Ljava/lang/String;)I, r1 >, < Ledu/nyu/websocket/ChatServer;, new, return value from edu.nyu.websocket.ChatServer.<init>(I)V, r2 >]
 51 getstatic       [< Ljava/io/BufferedReader;, new >, < Ljava/io/BufferedReader;, new >, < Ljava/io/InputStreamReader;, new >, < Ljava/io/InputStreamReader;, new >]::[< [Ljava/lang/String;, IP, r0 >, < I, return value from static java.lang.Integer.parseInt(Ljava/lang/String;)I, r1 >, < Ledu/nyu/websocket/ChatServer;, new, return value from edu.nyu.websocket.ChatServer.<init>(I)V, r2 >]
 54 invokespecial   [< Ljava/io/BufferedReader;, new >, < Ljava/io/BufferedReader;, new >, < Ljava/io/InputStreamReader;, new >, < Ljava/io/InputStreamReader;, new >, < Ljava/io/InputStream;, static java.lang.System.in Ljava/io/InputStream; >]::[< [Ljava/lang/String;, IP, r0 >, < I, return value from static java.lang.Integer.parseInt(Ljava/lang/String;)I, r1 >, < Ledu/nyu/websocket/ChatServer;, new, return value from edu.nyu.websocket.ChatServer.<init>(I)V, r2 >]
 57 invokespecial   [< Ljava/io/BufferedReader;, new >, < Ljava/io/BufferedReader;, new >, < Ljava/io/InputStreamReader;, new, return value from java.io.InputStreamReader.<init>(Ljava/io/InputStream;)V >]::[< [Ljava/lang/String;, IP, r0 >, < I, return value from static java.lang.Integer.parseInt(Ljava/lang/String;)I, r1 >, < Ledu/nyu/websocket/ChatServer;, new, return value from edu.nyu.websocket.ChatServer.<init>(I)V, r2 >]
 60 astore_3        [< Ljava/io/BufferedReader;, new, return value from java.io.BufferedReader.<init>(Ljava/io/Reader;)V >]::[< [Ljava/lang/String;, IP, r0 >, < I, return value from static java.lang.Integer.parseInt(Ljava/lang/String;)I, r1 >, < Ledu/nyu/websocket/ChatServer;, new, return value from edu.nyu.websocket.ChatServer.<init>(I)V, r2 >]
 61 aload_3         []::[< [Ljava/lang/String;, IP, r0 >, < I, return value from static java.lang.Integer.parseInt(Ljava/lang/String;)I, r1 >, < Ledu/nyu/websocket/ChatServer;, new, return value from edu.nyu.websocket.ChatServer.<init>(I)V, r2 >, < Ljava/io/BufferedReader;, new, return value from java.io.BufferedReader.<init>(Ljava/io/Reader;)V, r3 >]
 62 invokevirtual   [< Ljava/io/BufferedReader;, new, return value from java.io.BufferedReader.<init>(Ljava/io/Reader;)V, r3 >]::[< [Ljava/lang/String;, IP, r0 >, < I, return value from static java.lang.Integer.parseInt(Ljava/lang/String;)I, r1 >, < Ledu/nyu/websocket/ChatServer;, new, return value from edu.nyu.websocket.ChatServer.<init>(I)V, r2 >, < Ljava/io/BufferedReader;, new, return value from java.io.BufferedReader.<init>(Ljava/io/Reader;)V, r3 >]
 65 astore          [< Ljava/lang/String;, return value from java.io.BufferedReader.readLine()Ljava/lang/String; >]::[< [Ljava/lang/String;, IP, r0 >, < I, return value from static java.lang.Integer.parseInt(Ljava/lang/String;)I, r1 >, < Ledu/nyu/websocket/ChatServer;, new, return value from edu.nyu.websocket.ChatServer.<init>(I)V, r2 >, < Ljava/io/BufferedReader;, new, return value from java.io.BufferedReader.<init>(Ljava/io/Reader;)V, r3 >]
 67 aload_2         []::[< [Ljava/lang/String;, IP, r0 >, < I, return value from static java.lang.Integer.parseInt(Ljava/lang/String;)I, r1 >, < Ledu/nyu/websocket/ChatServer;, new, return value from edu.nyu.websocket.ChatServer.<init>(I)V, r2 >, < Ljava/io/BufferedReader;, new, return value from java.io.BufferedReader.<init>(Ljava/io/Reader;)V, r3 >, < Ljava/lang/String;, return value from java.io.BufferedReader.readLine()Ljava/lang/String;, r4 >]
 68 aload           [< Ledu/nyu/websocket/ChatServer;, new, return value from edu.nyu.websocket.ChatServer.<init>(I)V, r2 >]::[< [Ljava/lang/String;, IP, r0 >, < I, return value from static java.lang.Integer.parseInt(Ljava/lang/String;)I, r1 >, < Ledu/nyu/websocket/ChatServer;, new, return value from edu.nyu.websocket.ChatServer.<init>(I)V, r2 >, < Ljava/io/BufferedReader;, new, return value from java.io.BufferedReader.<init>(Ljava/io/Reader;)V, r3 >, < Ljava/lang/String;, return value from java.io.BufferedReader.readLine()Ljava/lang/String;, r4 >]
 70 invokevirtual   [< Ledu/nyu/websocket/ChatServer;, new, return value from edu.nyu.websocket.ChatServer.<init>(I)V, r2 >, < Ljava/lang/String;, return value from java.io.BufferedReader.readLine()Ljava/lang/String;, r4 >]::[< [Ljava/lang/String;, IP, r0 >, < I, return value from static java.lang.Integer.parseInt(Ljava/lang/String;)I, r1 >, < Ledu/nyu/websocket/ChatServer;, new, return value from edu.nyu.websocket.ChatServer.<init>(I)V, r2 >, < Ljava/io/BufferedReader;, new, return value from java.io.BufferedReader.<init>(Ljava/io/Reader;)V, r3 >, < Ljava/lang/String;, return value from java.io.BufferedReader.readLine()Ljava/lang/String;, r4 >]
 73 aload           []::[< [Ljava/lang/String;, IP, r0 >, < I, return value from static java.lang.Integer.parseInt(Ljava/lang/String;)I, r1 >, < Ledu/nyu/websocket/ChatServer;, new, return value from edu.nyu.websocket.ChatServer.<init>(I)V, r2 >, < Ljava/io/BufferedReader;, new, return value from java.io.BufferedReader.<init>(Ljava/io/Reader;)V, r3 >, < Ljava/lang/String;, return value from java.io.BufferedReader.readLine()Ljava/lang/String;, r4 >]
 75 ldc             [< Ljava/lang/String;, return value from java.io.BufferedReader.readLine()Ljava/lang/String;, r4 >]::[< [Ljava/lang/String;, IP, r0 >, < I, return value from static java.lang.Integer.parseInt(Ljava/lang/String;)I, r1 >, < Ledu/nyu/websocket/ChatServer;, new, return value from edu.nyu.websocket.ChatServer.<init>(I)V, r2 >, < Ljava/io/BufferedReader;, new, return value from java.io.BufferedReader.<init>(Ljava/io/Reader;)V, r3 >, < Ljava/lang/String;, return value from java.io.BufferedReader.readLine()Ljava/lang/String;, r4 >]
 77 invokevirtual   [< Ljava/lang/String;, return value from java.io.BufferedReader.readLine()Ljava/lang/String;, r4 >, < Ljava/lang/String;, "exit" >]::[< [Ljava/lang/String;, IP, r0 >, < I, return value from static java.lang.Integer.parseInt(Ljava/lang/String;)I, r1 >, < Ledu/nyu/websocket/ChatServer;, new, return value from edu.nyu.websocket.ChatServer.<init>(I)V, r2 >, < Ljava/io/BufferedReader;, new, return value from java.io.BufferedReader.<init>(Ljava/io/Reader;)V, r3 >, < Ljava/lang/String;, return value from java.io.BufferedReader.readLine()Ljava/lang/String;, r4 >]
 80 ifeq            [< Z, return value from java.lang.String.equals(Ljava/lang/Object;)Z >]::[< [Ljava/lang/String;, IP, r0 >, < I, return value from static java.lang.Integer.parseInt(Ljava/lang/String;)I, r1 >, < Ledu/nyu/websocket/ChatServer;, new, return value from edu.nyu.websocket.ChatServer.<init>(I)V, r2 >, < Ljava/io/BufferedReader;, new, return value from java.io.BufferedReader.<init>(Ljava/io/Reader;)V, r3 >, < Ljava/lang/String;, return value from java.io.BufferedReader.readLine()Ljava/lang/String;, r4 >]
 83 aload_2         []::[< [Ljava/lang/String;, IP, r0 >, < I, return value from static java.lang.Integer.parseInt(Ljava/lang/String;)I, r1 >, < Ledu/nyu/websocket/ChatServer;, new, return value from edu.nyu.websocket.ChatServer.<init>(I)V, r2 >, < Ljava/io/BufferedReader;, new, return value from java.io.BufferedReader.<init>(Ljava/io/Reader;)V, r3 >, < Ljava/lang/String;, return value from java.io.BufferedReader.readLine()Ljava/lang/String;, r4 >]
 84 sipush          [< Ledu/nyu/websocket/ChatServer;, new, return value from edu.nyu.websocket.ChatServer.<init>(I)V, r2 >]::[< [Ljava/lang/String;, IP, r0 >, < I, return value from static java.lang.Integer.parseInt(Ljava/lang/String;)I, r1 >, < Ledu/nyu/websocket/ChatServer;, new, return value from edu.nyu.websocket.ChatServer.<init>(I)V, r2 >, < Ljava/io/BufferedReader;, new, return value from java.io.BufferedReader.<init>(Ljava/io/Reader;)V, r3 >, < Ljava/lang/String;, return value from java.io.BufferedReader.readLine()Ljava/lang/String;, r4 >]
 87 invokevirtual   [< Ledu/nyu/websocket/ChatServer;, new, return value from edu.nyu.websocket.ChatServer.<init>(I)V, r2 >, < I, 1000 >]::[< [Ljava/lang/String;, IP, r0 >, < I, return value from static java.lang.Integer.parseInt(Ljava/lang/String;)I, r1 >, < Ledu/nyu/websocket/ChatServer;, new, return value from edu.nyu.websocket.ChatServer.<init>(I)V, r2 >, < Ljava/io/BufferedReader;, new, return value from java.io.BufferedReader.<init>(Ljava/io/Reader;)V, r3 >, < Ljava/lang/String;, return value from java.io.BufferedReader.readLine()Ljava/lang/String;, r4 >]
 90 goto            []::[< [Ljava/lang/String;, IP, r0 >, < I, return value from static java.lang.Integer.parseInt(Ljava/lang/String;)I, r1 >, < Ledu/nyu/websocket/ChatServer;, new, return value from edu.nyu.websocket.ChatServer.<init>(I)V, r2 >, < Ljava/io/BufferedReader;, new, return value from java.io.BufferedReader.<init>(Ljava/io/Reader;)V, r3 >, < Ljava/lang/String;, return value from java.io.BufferedReader.readLine()Ljava/lang/String;, r4 >]
 93 goto            []::[< [Ljava/lang/String;, IP, r0 >, < I, return value from static java.lang.Integer.parseInt(Ljava/lang/String;)I, r1 >, < Ledu/nyu/websocket/ChatServer;, new, return value from edu.nyu.websocket.ChatServer.<init>(I)V, r2 >, < Ljava/io/BufferedReader;, new, return value from java.io.BufferedReader.<init>(Ljava/io/Reader;)V, r3 >, < Ljava/lang/String;, return value from java.io.BufferedReader.readLine()Ljava/lang/String;, r4 >]
 96 return          []::[< [Ljava/lang/String;, IP, r0 >, < I, return value from static java.lang.Integer.parseInt(Ljava/lang/String;)I, r1 >, < Ledu/nyu/websocket/ChatServer;, new, return value from edu.nyu.websocket.ChatServer.<init>(I)V, r2 >, < Ljava/io/BufferedReader;, new, return value from java.io.BufferedReader.<init>(Ljava/io/Reader;)V, r3 >, < Ljava/lang/String;, return value from java.io.BufferedReader.readLine()Ljava/lang/String;, r4 >]

edu.nyu.websocket.ChatServer.onError : (Lorg.java_websocket.WebSocket;Ljava.lang.Exception;)V
  0 aload_2         []::[< Ledu/nyu/websocket/ChatServer;, IP, r0 >, < Lorg/java_websocket/WebSocket;, IP, r1 >, < Ljava/lang/Exception;, IP, r2 >]
  1 invokevirtual   [< Ljava/lang/Exception;, IP, r2 >]::[< Ledu/nyu/websocket/ChatServer;, IP, r0 >, < Lorg/java_websocket/WebSocket;, IP, r1 >, < Ljava/lang/Exception;, IP, r2 >]
  4 aload_1         []::[< Ledu/nyu/websocket/ChatServer;, IP, r0 >, < Lorg/java_websocket/WebSocket;, IP, r1 >, < Ljava/lang/Exception;, IP, r2 >]
  5 ifnull          [< Lorg/java_websocket/WebSocket;, IP, r1 >]::[< Ledu/nyu/websocket/ChatServer;, IP, r0 >, < Lorg/java_websocket/WebSocket;, IP, r1 >, < Ljava/lang/Exception;, IP, r2 >]
  8 return          []::[< Ledu/nyu/websocket/ChatServer;, IP, r0 >, < Lorg/java_websocket/WebSocket;, IP, r1 >, < Ljava/lang/Exception;, IP, r2 >]

edu.nyu.websocket.ChatServer.onStart : ()V
  0 getstatic       []::[< Ledu/nyu/websocket/ChatServer;, IP, r0 >]
  3 ldc             [< Ljava/io/PrintStream;, static java.lang.System.out Ljava/io/PrintStream; >]::[< Ledu/nyu/websocket/ChatServer;, IP, r0 >]
  5 invokevirtual   [< Ljava/io/PrintStream;, static java.lang.System.out Ljava/io/PrintStream; >, < Ljava/lang/String;, "Server started!" >]::[< Ledu/nyu/websocket/ChatServer;, IP, r0 >]
  8 aload_0         []::[< Ledu/nyu/websocket/ChatServer;, IP, r0 >]
  9 iconst_0        [< Ledu/nyu/websocket/ChatServer;, IP, r0 >]::[< Ledu/nyu/websocket/ChatServer;, IP, r0 >]
 10 invokevirtual   [< Ledu/nyu/websocket/ChatServer;, IP, r0 >, < I, 0 >]::[< Ledu/nyu/websocket/ChatServer;, IP, r0 >]
 13 aload_0         []::[< Ledu/nyu/websocket/ChatServer;, IP, r0 >]
 14 bipush          [< Ledu/nyu/websocket/ChatServer;, IP, r0 >]::[< Ledu/nyu/websocket/ChatServer;, IP, r0 >]
 16 invokevirtual   [< Ledu/nyu/websocket/ChatServer;, IP, r0 >, < I, 100 >]::[< Ledu/nyu/websocket/ChatServer;, IP, r0 >]
 19 return          []::[< Ledu/nyu/websocket/ChatServer;, IP, r0 >]
